
{
  "response": {
  "version":"0.1",
  "termsofService":"http://www.wunderground.com/weather/api/d/terms.html",
  "features": {
  "history": 1
  }
	}
		,
	"history": {
		"date": {
		"pretty": "September 25, 2008",
		"year": "2008",
		"mon": "09",
		"mday": "25",
		"hour": "12",
		"min": "00",
		"tzname": "America/Chicago"
		},
		"utcdate": {
		"pretty": "September 25, 2008",
		"year": "2008",
		"mon": "09",
		"mday": "25",
		"hour": "17",
		"min": "00",
		"tzname": "UTC"
		},
		"observations": [
		{
		"date": {
		"pretty": "12:51 AM CDT on September 25, 2008",
		"year": "2008",
		"mon": "09",
		"mday": "25",
		"hour": "00",
		"min": "51",
		"tzname": "America/Chicago"
		},
		"utcdate": {
		"pretty": "5:51 AM GMT on September 25, 2008",
		"year": "2008",
		"mon": "09",
		"mday": "25",
		"hour": "05",
		"min": "51",
		"tzname": "UTC"
		},
		"tempm":"21.1", "tempi":"70.0","dewptm":"16.7", "dewpti":"62.1","hum":"76","wspdm":"0.0", "wspdi":"0.0","wgustm":"-9999.0", "wgusti":"-9999.0","wdird":"0","wdire":"North","vism":"14.5", "visi":"9.0","pressurem":"1024.7", "pressurei":"30.26","windchillm":"-999", "windchilli":"-999","heatindexm":"-9999", "heatindexi":"-9999","precipm":"-9999.00", "precipi":"-9999.00","conds":"Overcast","icon":"cloudy","fog":"0","rain":"0","snow":"0","hail":"0","thunder":"0","tornado":"0","metar":"METAR KMDW 250551Z 00000KT 9SM BKN080 OVC250 21/17 A3028 RMK AO2 SLP247 T02110167 10256 20211 402780167 50001" },
		{
		"date": {
		"pretty": "1:51 AM CDT on September 25, 2008",
		"year": "2008",
		"mon": "09",
		"mday": "25",
		"hour": "01",
		"min": "51",
		"tzname": "America/Chicago"
		},
		"utcdate": {
		"pretty": "6:51 AM GMT on September 25, 2008",
		"year": "2008",
		"mon": "09",
		"mday": "25",
		"hour": "06",
		"min": "51",
		"tzname": "UTC"
		},
		"tempm":"21.7", "tempi":"71.1","dewptm":"17.2", "dewpti":"63.0","hum":"75","wspdm":"5.6", "wspdi":"3.5","wgustm":"-9999.0", "wgusti":"-9999.0","wdird":"50","wdire":"NE","vism":"14.5", "visi":"9.0","pressurem":"1024.6", "pressurei":"30.26","windchillm":"-999", "windchilli":"-999","heatindexm":"-9999", "heatindexi":"-9999","precipm":"-9999.00", "precipi":"-9999.00","conds":"Overcast","icon":"cloudy","fog":"0","rain":"0","snow":"0","hail":"0","thunder":"0","tornado":"0","metar":"METAR KMDW 250651Z 05003KT 9SM OVC090 22/17 A3028 RMK AO2 SLP246 T02170172" },
		{
		"date": {
		"pretty": "2:51 AM CDT on September 25, 2008",
		"year": "2008",
		"mon": "09",
		"mday": "25",
		"hour": "02",
		"min": "51",
		"tzname": "America/Chicago"
		},
		"utcdate": {
		"pretty": "7:51 AM GMT on September 25, 2008",
		"year": "2008",
		"mon": "09",
		"mday": "25",
		"hour": "07",
		"min": "51",
		"tzname": "UTC"
		},
		"tempm":"21.7", "tempi":"71.1","dewptm":"17.2", "dewpti":"63.0","hum":"75","wspdm":"5.6", "wspdi":"3.5","wgustm":"-9999.0", "wgusti":"-9999.0","wdird":"100","wdire":"East","vism":"11.3", "visi":"7.0","pressurem":"1024.4", "pressurei":"30.25","windchillm":"-999", "windchilli":"-999","heatindexm":"-9999", "heatindexi":"-9999","precipm":"-9999.00", "precipi":"-9999.00","conds":"Overcast","icon":"cloudy","fog":"0","rain":"0","snow":"0","hail":"0","thunder":"0","tornado":"0","metar":"METAR KMDW 250751Z 10003KT 7SM OVC100 22/17 A3028 RMK AO2 SLP244 T02170172" },
		{
		"date": {
		"pretty": "3:51 AM CDT on September 25, 2008",
		"year": "2008",
		"mon": "09",
		"mday": "25",
		"hour": "03",
		"min": "51",
		"tzname": "America/Chicago"
		},
		"utcdate": {
		"pretty": "8:51 AM GMT on September 25, 2008",
		"year": "2008",
		"mon": "09",
		"mday": "25",
		"hour": "08",
		"min": "51",
		"tzname": "UTC"
		},
		"tempm":"21.1", "tempi":"70.0","dewptm":"17.2", "dewpti":"63.0","hum":"78","wspdm":"0.0", "wspdi":"0.0","wgustm":"-9999.0", "wgusti":"-9999.0","wdird":"0","wdire":"North","vism":"12.9", "visi":"8.0","pressurem":"1024.4", "pressurei":"30.25","windchillm":"-999", "windchilli":"-999","heatindexm":"-9999", "heatindexi":"-9999","precipm":"-9999.00", "precipi":"-9999.00","conds":"Mostly Cloudy","icon":"mostlycloudy","fog":"0","rain":"0","snow":"0","hail":"0","thunder":"0","tornado":"0","metar":"METAR KMDW 250851Z 00000KT 8SM BKN100 BKN250 21/17 A3028 RMK AO2 SLP244 T02110172 56001" },
		{
		"date": {
		"pretty": "4:51 AM CDT on September 25, 2008",
		"year": "2008",
		"mon": "09",
		"mday": "25",
		"hour": "04",
		"min": "51",
		"tzname": "America/Chicago"
		},
		"utcdate": {
		"pretty": "9:51 AM GMT on September 25, 2008",
		"year": "2008",
		"mon": "09",
		"mday": "25",
		"hour": "09",
		"min": "51",
		"tzname": "UTC"
		},
		"tempm":"20.6", "tempi":"69.1","dewptm":"16.1", "dewpti":"61.0","hum":"75","wspdm":"7.4", "wspdi":"4.6","wgustm":"-9999.0", "wgusti":"-9999.0","wdird":"50","wdire":"NE","vism":"12.9", "visi":"8.0","pressurem":"1024.6", "pressurei":"30.26","windchillm":"-999", "windchilli":"-999","heatindexm":"-9999", "heatindexi":"-9999","precipm":"-9999.00", "precipi":"-9999.00","conds":"Partly Cloudy","icon":"partlycloudy","fog":"0","rain":"0","snow":"0","hail":"0","thunder":"0","tornado":"0","metar":"METAR KMDW 250951Z 05004KT 8SM FEW100 21/16 A3028 RMK AO2 SLP246 T02060161" },
		{
		"date": {
		"pretty": "5:51 AM CDT on September 25, 2008",
		"year": "2008",
		"mon": "09",
		"mday": "25",
		"hour": "05",
		"min": "51",
		"tzname": "America/Chicago"
		},
		"utcdate": {
		"pretty": "10:51 AM GMT on September 25, 2008",
		"year": "2008",
		"mon": "09",
		"mday": "25",
		"hour": "10",
		"min": "51",
		"tzname": "UTC"
		},
		"tempm":"19.4", "tempi":"66.9","dewptm":"17.8", "dewpti":"64.0","hum":"90","wspdm":"7.4", "wspdi":"4.6","wgustm":"-9999.0", "wgusti":"-9999.0","wdird":"10","wdire":"North","vism":"6.4", "visi":"4.0","pressurem":"1025.2", "pressurei":"30.28","windchillm":"-999", "windchilli":"-999","heatindexm":"-9999", "heatindexi":"-9999","precipm":"-9999.00", "precipi":"-9999.00","conds":"Clear","icon":"clear","fog":"0","rain":"0","snow":"0","hail":"0","thunder":"0","tornado":"0","metar":"METAR KMDW 251051Z 01004KT 4SM BR CLR 19/18 A3030 RMK AO2 SLP252 T01940178" },
		{
		"date": {
		"pretty": "6:51 AM CDT on September 25, 2008",
		"year": "2008",
		"mon": "09",
		"mday": "25",
		"hour": "06",
		"min": "51",
		"tzname": "America/Chicago"
		},
		"utcdate": {
		"pretty": "11:51 AM GMT on September 25, 2008",
		"year": "2008",
		"mon": "09",
		"mday": "25",
		"hour": "11",
		"min": "51",
		"tzname": "UTC"
		},
		"tempm":"19.4", "tempi":"66.9","dewptm":"17.2", "dewpti":"63.0","hum":"87","wspdm":"9.3", "wspdi":"5.8","wgustm":"-9999.0", "wgusti":"-9999.0","wdird":"10","wdire":"North","vism":"4.8", "visi":"3.0","pressurem":"1025.3", "pressurei":"30.28","windchillm":"-999", "windchilli":"-999","heatindexm":"-9999", "heatindexi":"-9999","precipm":"-9999.00", "precipi":"-9999.00","conds":"Clear","icon":"clear","fog":"0","rain":"0","snow":"0","hail":"0","thunder":"0","tornado":"0","metar":"METAR KMDW 251151Z 01005KT 3SM BR CLR 19/17 A3030 RMK AO2 SLP253 T01940172 10217 20189 53008" },
		{
		"date": {
		"pretty": "7:51 AM CDT on September 25, 2008",
		"year": "2008",
		"mon": "09",
		"mday": "25",
		"hour": "07",
		"min": "51",
		"tzname": "America/Chicago"
		},
		"utcdate": {
		"pretty": "12:51 PM GMT on September 25, 2008",
		"year": "2008",
		"mon": "09",
		"mday": "25",
		"hour": "12",
		"min": "51",
		"tzname": "UTC"
		},
		"tempm":"20.6", "tempi":"69.1","dewptm":"17.2", "dewpti":"63.0","hum":"81","wspdm":"9.3", "wspdi":"5.8","wgustm":"-9999.0", "wgusti":"-9999.0","wdird":"10","wdire":"North","vism":"4.8", "visi":"3.0","pressurem":"1025.7", "pressurei":"30.29","windchillm":"-999", "windchilli":"-999","heatindexm":"-9999", "heatindexi":"-9999","precipm":"-9999.00", "precipi":"-9999.00","conds":"Haze","icon":"hazy","fog":"0","rain":"0","snow":"0","hail":"0","thunder":"0","tornado":"0","metar":"METAR KMDW 251251Z 01005KT 3SM HZ CLR 21/17 A3031 RMK AO2 SLP257 T02060172" },
		{
		"date": {
		"pretty": "8:51 AM CDT on September 25, 2008",
		"year": "2008",
		"mon": "09",
		"mday": "25",
		"hour": "08",
		"min": "51",
		"tzname": "America/Chicago"
		},
		"utcdate": {
		"pretty": "1:51 PM GMT on September 25, 2008",
		"year": "2008",
		"mon": "09",
		"mday": "25",
		"hour": "13",
		"min": "51",
		"tzname": "UTC"
		},
		"tempm":"21.7", "tempi":"71.1","dewptm":"16.1", "dewpti":"61.0","hum":"70","wspdm":"14.8", "wspdi":"9.2","wgustm":"-9999.0", "wgusti":"-9999.0","wdird":"20","wdire":"NNE","vism":"8.0", "visi":"5.0","pressurem":"1025.9", "pressurei":"30.30","windchillm":"-999", "windchilli":"-999","heatindexm":"-9999", "heatindexi":"-9999","precipm":"-9999.00", "precipi":"-9999.00","conds":"Haze","icon":"hazy","fog":"0","rain":"0","snow":"0","hail":"0","thunder":"0","tornado":"0","metar":"METAR KMDW 251351Z 02008KT 5SM HZ FEW250 22/16 A3032 RMK AO2 SLP259 T02170161" },
		{
		"date": {
		"pretty": "9:51 AM CDT on September 25, 2008",
		"year": "2008",
		"mon": "09",
		"mday": "25",
		"hour": "09",
		"min": "51",
		"tzname": "America/Chicago"
		},
		"utcdate": {
		"pretty": "2:51 PM GMT on September 25, 2008",
		"year": "2008",
		"mon": "09",
		"mday": "25",
		"hour": "14",
		"min": "51",
		"tzname": "UTC"
		},
		"tempm":"22.8", "tempi":"73.0","dewptm":"16.1", "dewpti":"61.0","hum":"66","wspdm":"13.0", "wspdi":"8.1","wgustm":"-9999.0", "wgusti":"-9999.0","wdird":"20","wdire":"NNE","vism":"11.3", "visi":"7.0","pressurem":"1026.0", "pressurei":"30.30","windchillm":"-999", "windchilli":"-999","heatindexm":"-9999", "heatindexi":"-9999","precipm":"-9999.00", "precipi":"-9999.00","conds":"Scattered Clouds","icon":"partlycloudy","fog":"0","rain":"0","snow":"0","hail":"0","thunder":"0","tornado":"0","metar":"METAR KMDW 251451Z 02007KT 7SM FEW080 SCT250 23/16 A3032 RMK AO2 SLP260 T02280161 51006" },
		{
		"date": {
		"pretty": "10:51 AM CDT on September 25, 2008",
		"year": "2008",
		"mon": "09",
		"mday": "25",
		"hour": "10",
		"min": "51",
		"tzname": "America/Chicago"
		},
		"utcdate": {
		"pretty": "3:51 PM GMT on September 25, 2008",
		"year": "2008",
		"mon": "09",
		"mday": "25",
		"hour": "15",
		"min": "51",
		"tzname": "UTC"
		},
		"tempm":"22.8", "tempi":"73.0","dewptm":"16.1", "dewpti":"61.0","hum":"66","wspdm":"16.7", "wspdi":"10.4","wgustm":"-9999.0", "wgusti":"-9999.0","wdird":"50","wdire":"NE","vism":"11.3", "visi":"7.0","pressurem":"1025.9", "pressurei":"30.30","windchillm":"-999", "windchilli":"-999","heatindexm":"-9999", "heatindexi":"-9999","precipm":"-9999.00", "precipi":"-9999.00","conds":"Overcast","icon":"cloudy","fog":"0","rain":"0","snow":"0","hail":"0","thunder":"0","tornado":"0","metar":"METAR KMDW 251551Z 05009KT 7SM BKN085 OVC250 23/16 A3032 RMK AO2 SLP259 T02280161" },
		{
		"date": {
		"pretty": "11:51 AM CDT on September 25, 2008",
		"year": "2008",
		"mon": "09",
		"mday": "25",
		"hour": "11",
		"min": "51",
		"tzname": "America/Chicago"
		},
		"utcdate": {
		"pretty": "4:51 PM GMT on September 25, 2008",
		"year": "2008",
		"mon": "09",
		"mday": "25",
		"hour": "16",
		"min": "51",
		"tzname": "UTC"
		},
		"tempm":"23.9", "tempi":"75.0","dewptm":"15.0", "dewpti":"59.0","hum":"57","wspdm":"16.7", "wspdi":"10.4","wgustm":"-9999.0", "wgusti":"-9999.0","wdird":"20","wdire":"NNE","vism":"14.5", "visi":"9.0","pressurem":"1025.5", "pressurei":"30.29","windchillm":"-999", "windchilli":"-999","heatindexm":"-9999", "heatindexi":"-9999","precipm":"-9999.00", "precipi":"-9999.00","conds":"Mostly Cloudy","icon":"mostlycloudy","fog":"0","rain":"0","snow":"0","hail":"0","thunder":"0","tornado":"0","metar":"METAR KMDW 251651Z 02009KT 9SM BKN090 BKN250 24/15 A3031 RMK AO2 SLP255 T02390150" },
		{
		"date": {
		"pretty": "12:51 PM CDT on September 25, 2008",
		"year": "2008",
		"mon": "09",
		"mday": "25",
		"hour": "12",
		"min": "51",
		"tzname": "America/Chicago"
		},
		"utcdate": {
		"pretty": "5:51 PM GMT on September 25, 2008",
		"year": "2008",
		"mon": "09",
		"mday": "25",
		"hour": "17",
		"min": "51",
		"tzname": "UTC"
		},
		"tempm":"25.0", "tempi":"77.0","dewptm":"16.1", "dewpti":"61.0","hum":"58","wspdm":"11.1", "wspdi":"6.9","wgustm":"-9999.0", "wgusti":"-9999.0","wdird":"10","wdire":"North","vism":"11.3", "visi":"7.0","pressurem":"1025.3", "pressurei":"30.28","windchillm":"-999", "windchilli":"-999","heatindexm":"-9999", "heatindexi":"-9999","precipm":"-9999.00", "precipi":"-9999.00","conds":"Mostly Cloudy","icon":"mostlycloudy","fog":"0","rain":"0","snow":"0","hail":"0","thunder":"0","tornado":"0","metar":"METAR KMDW 251751Z 01006KT 7SM FEW090 BKN250 25/16 A3030 RMK AO2 SLP253 T02500161 10250 20194 58006" },
		{
		"date": {
		"pretty": "1:51 PM CDT on September 25, 2008",
		"year": "2008",
		"mon": "09",
		"mday": "25",
		"hour": "13",
		"min": "51",
		"tzname": "America/Chicago"
		},
		"utcdate": {
		"pretty": "6:51 PM GMT on September 25, 2008",
		"year": "2008",
		"mon": "09",
		"mday": "25",
		"hour": "18",
		"min": "51",
		"tzname": "UTC"
		},
		"tempm":"25.0", "tempi":"77.0","dewptm":"15.6", "dewpti":"60.1","hum":"56","wspdm":"16.7", "wspdi":"10.4","wgustm":"-9999.0", "wgusti":"-9999.0","wdird":"40","wdire":"NE","vism":"14.5", "visi":"9.0","pressurem":"1024.8", "pressurei":"30.27","windchillm":"-999", "windchilli":"-999","heatindexm":"-9999", "heatindexi":"-9999","precipm":"-9999.00", "precipi":"-9999.00","conds":"Scattered Clouds","icon":"partlycloudy","fog":"0","rain":"0","snow":"0","hail":"0","thunder":"0","tornado":"0","metar":"METAR KMDW 251851Z 04009KT 9SM FEW090 SCT250 25/16 A3029 RMK AO2 SLP248 T02500156" },
		{
		"date": {
		"pretty": "2:51 PM CDT on September 25, 2008",
		"year": "2008",
		"mon": "09",
		"mday": "25",
		"hour": "14",
		"min": "51",
		"tzname": "America/Chicago"
		},
		"utcdate": {
		"pretty": "7:51 PM GMT on September 25, 2008",
		"year": "2008",
		"mon": "09",
		"mday": "25",
		"hour": "19",
		"min": "51",
		"tzname": "UTC"
		},
		"tempm":"25.0", "tempi":"77.0","dewptm":"14.4", "dewpti":"57.9","hum":"52","wspdm":"16.7", "wspdi":"10.4","wgustm":"-9999.0", "wgusti":"-9999.0","wdird":"30","wdire":"NNE","vism":"16.1", "visi":"10.0","pressurem":"1024.4", "pressurei":"30.25","windchillm":"-999", "windchilli":"-999","heatindexm":"-9999", "heatindexi":"-9999","precipm":"-9999.00", "precipi":"-9999.00","conds":"Scattered Clouds","icon":"partlycloudy","fog":"0","rain":"0","snow":"0","hail":"0","thunder":"0","tornado":"0","metar":"METAR KMDW 251951Z 03009KT 10SM FEW110 SCT250 25/14 A3028 RMK AO2 SLP244 T02500144" },
		{
		"date": {
		"pretty": "3:51 PM CDT on September 25, 2008",
		"year": "2008",
		"mon": "09",
		"mday": "25",
		"hour": "15",
		"min": "51",
		"tzname": "America/Chicago"
		},
		"utcdate": {
		"pretty": "8:51 PM GMT on September 25, 2008",
		"year": "2008",
		"mon": "09",
		"mday": "25",
		"hour": "20",
		"min": "51",
		"tzname": "UTC"
		},
		"tempm":"25.0", "tempi":"77.0","dewptm":"13.3", "dewpti":"55.9","hum":"48","wspdm":"9.3", "wspdi":"5.8","wgustm":"-9999.0", "wgusti":"-9999.0","wdird":"60","wdire":"ENE","vism":"14.5", "visi":"9.0","pressurem":"1023.8", "pressurei":"30.24","windchillm":"-999", "windchilli":"-999","heatindexm":"-9999", "heatindexi":"-9999","precipm":"-9999.00", "precipi":"-9999.00","conds":"Partly Cloudy","icon":"partlycloudy","fog":"0","rain":"0","snow":"0","hail":"0","thunder":"0","tornado":"0","metar":"METAR KMDW 252051Z 06005KT 9SM FEW250 25/13 A3026 RMK AO2 SLP238 T02500133 58015" },
		{
		"date": {
		"pretty": "4:51 PM CDT on September 25, 2008",
		"year": "2008",
		"mon": "09",
		"mday": "25",
		"hour": "16",
		"min": "51",
		"tzname": "America/Chicago"
		},
		"utcdate": {
		"pretty": "9:51 PM GMT on September 25, 2008",
		"year": "2008",
		"mon": "09",
		"mday": "25",
		"hour": "21",
		"min": "51",
		"tzname": "UTC"
		},
		"tempm":"24.4", "tempi":"75.9","dewptm":"13.9", "dewpti":"57.0","hum":"52","wspdm":"11.1", "wspdi":"6.9","wgustm":"-9999.0", "wgusti":"-9999.0","wdird":"80","wdire":"East","vism":"14.5", "visi":"9.0","pressurem":"1023.2", "pressurei":"30.22","windchillm":"-999", "windchilli":"-999","heatindexm":"-9999", "heatindexi":"-9999","precipm":"-9999.00", "precipi":"-9999.00","conds":"Scattered Clouds","icon":"partlycloudy","fog":"0","rain":"0","snow":"0","hail":"0","thunder":"0","tornado":"0","metar":"METAR KMDW 252151Z 08006KT 9SM SCT250 24/14 A3024 RMK AO2 SLP232 T02440139" },
		{
		"date": {
		"pretty": "5:51 PM CDT on September 25, 2008",
		"year": "2008",
		"mon": "09",
		"mday": "25",
		"hour": "17",
		"min": "51",
		"tzname": "America/Chicago"
		},
		"utcdate": {
		"pretty": "10:51 PM GMT on September 25, 2008",
		"year": "2008",
		"mon": "09",
		"mday": "25",
		"hour": "22",
		"min": "51",
		"tzname": "UTC"
		},
		"tempm":"23.9", "tempi":"75.0","dewptm":"13.3", "dewpti":"55.9","hum":"51","wspdm":"9.3", "wspdi":"5.8","wgustm":"-9999.0", "wgusti":"-9999.0","wdird":"80","wdire":"East","vism":"14.5", "visi":"9.0","pressurem":"1023.2", "pressurei":"30.22","windchillm":"-999", "windchilli":"-999","heatindexm":"-9999", "heatindexi":"-9999","precipm":"-9999.00", "precipi":"-9999.00","conds":"Scattered Clouds","icon":"partlycloudy","fog":"0","rain":"0","snow":"0","hail":"0","thunder":"0","tornado":"0","metar":"METAR KMDW 252251Z 08005KT 9SM FEW200 SCT250 24/13 A3024 RMK AO2 SLP232 T02390133" },
		{
		"date": {
		"pretty": "6:51 PM CDT on September 25, 2008",
		"year": "2008",
		"mon": "09",
		"mday": "25",
		"hour": "18",
		"min": "51",
		"tzname": "America/Chicago"
		},
		"utcdate": {
		"pretty": "11:51 PM GMT on September 25, 2008",
		"year": "2008",
		"mon": "09",
		"mday": "25",
		"hour": "23",
		"min": "51",
		"tzname": "UTC"
		},
		"tempm":"21.7", "tempi":"71.1","dewptm":"15.6", "dewpti":"60.1","hum":"68","wspdm":"11.1", "wspdi":"6.9","wgustm":"-9999.0", "wgusti":"-9999.0","wdird":"30","wdire":"NNE","vism":"12.9", "visi":"8.0","pressurem":"1023.0", "pressurei":"30.21","windchillm":"-999", "windchilli":"-999","heatindexm":"-9999", "heatindexi":"-9999","precipm":"-9999.00", "precipi":"-9999.00","conds":"Scattered Clouds","icon":"partlycloudy","fog":"0","rain":"0","snow":"0","hail":"0","thunder":"0","tornado":"0","metar":"METAR KMDW 252351Z 03006KT 8SM FEW200 SCT250 22/16 A3023 RMK AO2 SLP230 T02170156 10256 20217 56009" },
		{
		"date": {
		"pretty": "7:51 PM CDT on September 25, 2008",
		"year": "2008",
		"mon": "09",
		"mday": "25",
		"hour": "19",
		"min": "51",
		"tzname": "America/Chicago"
		},
		"utcdate": {
		"pretty": "12:51 AM GMT on September 26, 2008",
		"year": "2008",
		"mon": "09",
		"mday": "26",
		"hour": "00",
		"min": "51",
		"tzname": "UTC"
		},
		"tempm":"20.6", "tempi":"69.1","dewptm":"16.1", "dewpti":"61.0","hum":"75","wspdm":"13.0", "wspdi":"8.1","wgustm":"-9999.0", "wgusti":"-9999.0","wdird":"30","wdire":"NNE","vism":"11.3", "visi":"7.0","pressurem":"1023.4", "pressurei":"30.22","windchillm":"-999", "windchilli":"-999","heatindexm":"-9999", "heatindexi":"-9999","precipm":"-9999.00", "precipi":"-9999.00","conds":"Scattered Clouds","icon":"partlycloudy","fog":"0","rain":"0","snow":"0","hail":"0","thunder":"0","tornado":"0","metar":"METAR KMDW 260051Z 03007KT 7SM FEW200 SCT250 21/16 A3024 RMK AO2 SLP234 T02060161" },
		{
		"date": {
		"pretty": "8:51 PM CDT on September 25, 2008",
		"year": "2008",
		"mon": "09",
		"mday": "25",
		"hour": "20",
		"min": "51",
		"tzname": "America/Chicago"
		},
		"utcdate": {
		"pretty": "1:51 AM GMT on September 26, 2008",
		"year": "2008",
		"mon": "09",
		"mday": "26",
		"hour": "01",
		"min": "51",
		"tzname": "UTC"
		},
		"tempm":"20.0", "tempi":"68.0","dewptm":"16.7", "dewpti":"62.1","hum":"81","wspdm":"11.1", "wspdi":"6.9","wgustm":"-9999.0", "wgusti":"-9999.0","wdird":"70","wdire":"ENE","vism":"9.7", "visi":"6.0","pressurem":"1023.6", "pressurei":"30.23","windchillm":"-999", "windchilli":"-999","heatindexm":"-9999", "heatindexi":"-9999","precipm":"-9999.00", "precipi":"-9999.00","conds":"Haze","icon":"hazy","fog":"0","rain":"0","snow":"0","hail":"0","thunder":"0","tornado":"0","metar":"METAR KMDW 260151Z 07006KT 6SM HZ FEW250 20/17 A3025 RMK AO2 SLP236 T02000167" },
		{
		"date": {
		"pretty": "9:51 PM CDT on September 25, 2008",
		"year": "2008",
		"mon": "09",
		"mday": "25",
		"hour": "21",
		"min": "51",
		"tzname": "America/Chicago"
		},
		"utcdate": {
		"pretty": "2:51 AM GMT on September 26, 2008",
		"year": "2008",
		"mon": "09",
		"mday": "26",
		"hour": "02",
		"min": "51",
		"tzname": "UTC"
		},
		"tempm":"19.4", "tempi":"66.9","dewptm":"16.7", "dewpti":"62.1","hum":"84","wspdm":"9.3", "wspdi":"5.8","wgustm":"-9999.0", "wgusti":"-9999.0","wdird":"80","wdire":"East","vism":"8.0", "visi":"5.0","pressurem":"1023.6", "pressurei":"30.23","windchillm":"-999", "windchilli":"-999","heatindexm":"-9999", "heatindexi":"-9999","precipm":"-9999.00", "precipi":"-9999.00","conds":"Haze","icon":"hazy","fog":"0","rain":"0","snow":"0","hail":"0","thunder":"0","tornado":"0","metar":"METAR KMDW 260251Z 08005KT 5SM HZ FEW250 19/17 A3025 RMK AO2 SLP236 T01940167 50005" },
		{
		"date": {
		"pretty": "10:51 PM CDT on September 25, 2008",
		"year": "2008",
		"mon": "09",
		"mday": "25",
		"hour": "22",
		"min": "51",
		"tzname": "America/Chicago"
		},
		"utcdate": {
		"pretty": "3:51 AM GMT on September 26, 2008",
		"year": "2008",
		"mon": "09",
		"mday": "26",
		"hour": "03",
		"min": "51",
		"tzname": "UTC"
		},
		"tempm":"19.4", "tempi":"66.9","dewptm":"16.1", "dewpti":"61.0","hum":"81","wspdm":"7.4", "wspdi":"4.6","wgustm":"-9999.0", "wgusti":"-9999.0","wdird":"10","wdire":"North","vism":"6.4", "visi":"4.0","pressurem":"1023.7", "pressurei":"30.23","windchillm":"-999", "windchilli":"-999","heatindexm":"-9999", "heatindexi":"-9999","precipm":"-9999.00", "precipi":"-9999.00","conds":"Haze","icon":"hazy","fog":"0","rain":"0","snow":"0","hail":"0","thunder":"0","tornado":"0","metar":"METAR KMDW 260351Z 01004KT 4SM HZ FEW250 19/16 A3025 RMK AO2 SLP237 T01940161" },
		{
		"date": {
		"pretty": "11:51 PM CDT on September 25, 2008",
		"year": "2008",
		"mon": "09",
		"mday": "25",
		"hour": "23",
		"min": "51",
		"tzname": "America/Chicago"
		},
		"utcdate": {
		"pretty": "4:51 AM GMT on September 26, 2008",
		"year": "2008",
		"mon": "09",
		"mday": "26",
		"hour": "04",
		"min": "51",
		"tzname": "UTC"
		},
		"tempm":"19.4", "tempi":"66.9","dewptm":"17.2", "dewpti":"63.0","hum":"87","wspdm":"0.0", "wspdi":"0.0","wgustm":"-9999.0", "wgusti":"-9999.0","wdird":"0","wdire":"North","vism":"6.4", "visi":"4.0","pressurem":"1023.1", "pressurei":"30.22","windchillm":"-999", "windchilli":"-999","heatindexm":"-9999", "heatindexi":"-9999","precipm":"-9999.00", "precipi":"-9999.00","conds":"Clear","icon":"clear","fog":"0","rain":"0","snow":"0","hail":"0","thunder":"0","tornado":"0","metar":"METAR KMDW 260451Z 00000KT 4SM BR CLR 19/17 A3024 RMK AO2 SLP231 T01940172" }
		],
		"dailysummary": [
		{ "date": {
		"pretty": "12:00 PM CDT on September 25, 2008",
		"year": "2008",
		"mon": "09",
		"mday": "25",
		"hour": "12",
		"min": "00",
		"tzname": "America/Chicago"
		},
		"fog":"0","rain":"0","snow":"0","snowfallm":"0.00", "snowfalli":"0.00","monthtodatesnowfallm":"", "monthtodatesnowfalli":"","since1julsnowfallm":"", "since1julsnowfalli":"","snowdepthm":"", "snowdepthi":"","hail":"0","thunder":"0","tornado":"0","meantempm":"22", "meantempi":"72","meandewptm":"16", "meandewpti":"61","meanpressurem":"1025", "meanpressurei":"30.26","meanwindspdm":"8", "meanwindspdi":"5","meanwdire":"","meanwdird":"40","meanvism":"11", "meanvisi":"7","humidity":"","maxtempm":"26", "maxtempi":"78","mintempm":"19", "mintempi":"66","maxhumidity":"90","minhumidity":"48","maxdewptm":"18", "maxdewpti":"64","mindewptm":"13", "mindewpti":"56","maxpressurem":"1026", "maxpressurei":"30.30","minpressurem":"1023", "minpressurei":"30.21","maxwspdm":"16", "maxwspdi":"10","minwspdm":"0", "minwspdi":"0","maxvism":"16", "maxvisi":"10","minvism":"5", "minvisi":"3","gdegreedays":"22","heatingdegreedays":"0","coolingdegreedays":"6","precipm":"0.00", "precipi":"0.00","precipsource":"","heatingdegreedaysnormal":"","monthtodateheatingdegreedays":"","monthtodateheatingdegreedaysnormal":"","since1sepheatingdegreedays":"","since1sepheatingdegreedaysnormal":"","since1julheatingdegreedays":"","since1julheatingdegreedaysnormal":"","coolingdegreedaysnormal":"","monthtodatecoolingdegreedays":"","monthtodatecoolingdegreedaysnormal":"","since1sepcoolingdegreedays":"","since1sepcoolingdegreedaysnormal":"","since1jancoolingdegreedays":"","since1jancoolingdegreedaysnormal":"" }
		]
	}
}
