
{
  "response": {
  "version":"0.1",
  "termsofService":"http://www.wunderground.com/weather/api/d/terms.html",
  "features": {
  "history": 1
  }
	}
		,
	"history": {
		"date": {
		"pretty": "May 29, 2011",
		"year": "2011",
		"mon": "05",
		"mday": "29",
		"hour": "12",
		"min": "00",
		"tzname": "America/Chicago"
		},
		"utcdate": {
		"pretty": "May 29, 2011",
		"year": "2011",
		"mon": "05",
		"mday": "29",
		"hour": "17",
		"min": "00",
		"tzname": "UTC"
		},
		"observations": [
		{
		"date": {
		"pretty": "12:20 AM CDT on May 29, 2011",
		"year": "2011",
		"mon": "05",
		"mday": "29",
		"hour": "00",
		"min": "20",
		"tzname": "America/Chicago"
		},
		"utcdate": {
		"pretty": "5:20 AM GMT on May 29, 2011",
		"year": "2011",
		"mon": "05",
		"mday": "29",
		"hour": "05",
		"min": "20",
		"tzname": "UTC"
		},
		"tempm":"15.0", "tempi":"59.0","dewptm":"14.0", "dewpti":"57.2","hum":"94","wspdm":"5.6", "wspdi":"3.5","wgustm":"-9999.0", "wgusti":"-9999.0","wdird":"120","wdire":"ESE","vism":"3.2", "visi":"2.0","pressurem":"1010.4", "pressurei":"29.84","windchillm":"-999", "windchilli":"-999","heatindexm":"-9999", "heatindexi":"-9999","precipm":"-9999.00", "precipi":"-9999.00","conds":"Mostly Cloudy","icon":"mostlycloudy","fog":"0","rain":"0","snow":"0","hail":"0","thunder":"0","tornado":"0","metar":"SPECI KMDW 290520Z 12003KT 2SM BR FEW043 BKN060 15/14 A2984 RMK AO2" },
		{
		"date": {
		"pretty": "12:51 AM CDT on May 29, 2011",
		"year": "2011",
		"mon": "05",
		"mday": "29",
		"hour": "00",
		"min": "51",
		"tzname": "America/Chicago"
		},
		"utcdate": {
		"pretty": "5:51 AM GMT on May 29, 2011",
		"year": "2011",
		"mon": "05",
		"mday": "29",
		"hour": "05",
		"min": "51",
		"tzname": "UTC"
		},
		"tempm":"15.0", "tempi":"59.0","dewptm":"14.4", "dewpti":"57.9","hum":"96","wspdm":"0.0", "wspdi":"0.0","wgustm":"-9999.0", "wgusti":"-9999.0","wdird":"0","wdire":"North","vism":"3.2", "visi":"2.0","pressurem":"1009.7", "pressurei":"29.82","windchillm":"-999", "windchilli":"-999","heatindexm":"-9999", "heatindexi":"-9999","precipm":"-9999.00", "precipi":"-9999.00","conds":"Scattered Clouds","icon":"partlycloudy","fog":"0","rain":"0","snow":"0","hail":"0","thunder":"0","tornado":"0","metar":"METAR KMDW 290551Z 00000KT 2SM BR FEW060 SCT250 15/14 A2983 RMK AO2 SLP097 60000 T01500144 10161 20144 401780111 58004" },
		{
		"date": {
		"pretty": "12:57 AM CDT on May 29, 2011",
		"year": "2011",
		"mon": "05",
		"mday": "29",
		"hour": "00",
		"min": "57",
		"tzname": "America/Chicago"
		},
		"utcdate": {
		"pretty": "5:57 AM GMT on May 29, 2011",
		"year": "2011",
		"mon": "05",
		"mday": "29",
		"hour": "05",
		"min": "57",
		"tzname": "UTC"
		},
		"tempm":"14.0", "tempi":"57.2","dewptm":"14.0", "dewpti":"57.2","hum":"100","wspdm":"0.0", "wspdi":"0.0","wgustm":"-9999.0", "wgusti":"-9999.0","wdird":"0","wdire":"North","vism":"2.4", "visi":"1.5","pressurem":"1010.0", "pressurei":"29.83","windchillm":"-999", "windchilli":"-999","heatindexm":"-9999", "heatindexi":"-9999","precipm":"-9999.00", "precipi":"-9999.00","conds":"Scattered Clouds","icon":"partlycloudy","fog":"0","rain":"0","snow":"0","hail":"0","thunder":"0","tornado":"0","metar":"SPECI KMDW 290557Z 00000KT 1 1/2SM BR FEW001 SCT060 SCT250 14/14 A2983 RMK AO2" },
		{
		"date": {
		"pretty": "1:17 AM CDT on May 29, 2011",
		"year": "2011",
		"mon": "05",
		"mday": "29",
		"hour": "01",
		"min": "17",
		"tzname": "America/Chicago"
		},
		"utcdate": {
		"pretty": "6:17 AM GMT on May 29, 2011",
		"year": "2011",
		"mon": "05",
		"mday": "29",
		"hour": "06",
		"min": "17",
		"tzname": "UTC"
		},
		"tempm":"14.0", "tempi":"57.2","dewptm":"14.0", "dewpti":"57.2","hum":"100","wspdm":"0.0", "wspdi":"0.0","wgustm":"-9999.0", "wgusti":"-9999.0","wdird":"0","wdire":"North","vism":"1.2", "visi":"0.8","pressurem":"1010.0", "pressurei":"29.83","windchillm":"-999", "windchilli":"-999","heatindexm":"-9999", "heatindexi":"-9999","precipm":"-9999.00", "precipi":"-9999.00","conds":"Scattered Clouds","icon":"partlycloudy","fog":"0","rain":"0","snow":"0","hail":"0","thunder":"0","tornado":"0","metar":"SPECI KMDW 290617Z 00000KT 3/4SM R31C/4500FT BR SCT001 14/14 A2983 RMK AO2" },
		{
		"date": {
		"pretty": "1:21 AM CDT on May 29, 2011",
		"year": "2011",
		"mon": "05",
		"mday": "29",
		"hour": "01",
		"min": "21",
		"tzname": "America/Chicago"
		},
		"utcdate": {
		"pretty": "6:21 AM GMT on May 29, 2011",
		"year": "2011",
		"mon": "05",
		"mday": "29",
		"hour": "06",
		"min": "21",
		"tzname": "UTC"
		},
		"tempm":"14.0", "tempi":"57.2","dewptm":"14.0", "dewpti":"57.2","hum":"100","wspdm":"0.0", "wspdi":"0.0","wgustm":"-9999.0", "wgusti":"-9999.0","wdird":"0","wdire":"North","vism":"0.8", "visi":"0.5","pressurem":"1010.0", "pressurei":"29.83","windchillm":"-999", "windchilli":"-999","heatindexm":"-9999", "heatindexi":"-9999","precipm":"-9999.00", "precipi":"-9999.00","conds":"Fog","icon":"fog","fog":"1","rain":"0","snow":"0","hail":"0","thunder":"0","tornado":"0","metar":"SPECI KMDW 290621Z 00000KT 1/2SM R31C/3000FT FG VV002 14/14 A2983 RMK AO2" },
		{
		"date": {
		"pretty": "1:30 AM CDT on May 29, 2011",
		"year": "2011",
		"mon": "05",
		"mday": "29",
		"hour": "01",
		"min": "30",
		"tzname": "America/Chicago"
		},
		"utcdate": {
		"pretty": "6:30 AM GMT on May 29, 2011",
		"year": "2011",
		"mon": "05",
		"mday": "29",
		"hour": "06",
		"min": "30",
		"tzname": "UTC"
		},
		"tempm":"14.0", "tempi":"57.2","dewptm":"14.0", "dewpti":"57.2","hum":"100","wspdm":"0.0", "wspdi":"0.0","wgustm":"-9999.0", "wgusti":"-9999.0","wdird":"0","wdire":"North","vism":"0.4", "visi":"0.2","pressurem":"1010.0", "pressurei":"29.83","windchillm":"-999", "windchilli":"-999","heatindexm":"-9999", "heatindexi":"-9999","precipm":"-9999.00", "precipi":"-9999.00","conds":"Fog","icon":"fog","fog":"1","rain":"0","snow":"0","hail":"0","thunder":"0","tornado":"0","metar":"SPECI KMDW 290630Z 00000KT 1/4SM R31C/1000FT FG VV001 14/14 A2983 RMK AO2" },
		{
		"date": {
		"pretty": "1:51 AM CDT on May 29, 2011",
		"year": "2011",
		"mon": "05",
		"mday": "29",
		"hour": "01",
		"min": "51",
		"tzname": "America/Chicago"
		},
		"utcdate": {
		"pretty": "6:51 AM GMT on May 29, 2011",
		"year": "2011",
		"mon": "05",
		"mday": "29",
		"hour": "06",
		"min": "51",
		"tzname": "UTC"
		},
		"tempm":"13.9", "tempi":"57.0","dewptm":"13.9", "dewpti":"57.0","hum":"100","wspdm":"0.0", "wspdi":"0.0","wgustm":"-9999.0", "wgusti":"-9999.0","wdird":"0","wdire":"North","vism":"0.2", "visi":"0.1","pressurem":"1009.6", "pressurei":"29.82","windchillm":"-999", "windchilli":"-999","heatindexm":"-9999", "heatindexi":"-9999","precipm":"-9999.00", "precipi":"-9999.00","conds":"Fog","icon":"fog","fog":"1","rain":"0","snow":"0","hail":"0","thunder":"0","tornado":"0","metar":"METAR KMDW 290651Z 00000KT 1/8SM R31C/0800FT FG VV001 14/14 A2982 RMK AO2 SLP096 T01390139" },
		{
		"date": {
		"pretty": "2:30 AM CDT on May 29, 2011",
		"year": "2011",
		"mon": "05",
		"mday": "29",
		"hour": "02",
		"min": "30",
		"tzname": "America/Chicago"
		},
		"utcdate": {
		"pretty": "7:30 AM GMT on May 29, 2011",
		"year": "2011",
		"mon": "05",
		"mday": "29",
		"hour": "07",
		"min": "30",
		"tzname": "UTC"
		},
		"tempm":"14.0", "tempi":"57.2","dewptm":"14.0", "dewpti":"57.2","hum":"100","wspdm":"5.6", "wspdi":"3.5","wgustm":"-9999.0", "wgusti":"-9999.0","wdird":"110","wdire":"ESE","vism":"0.8", "visi":"0.5","pressurem":"1009.7", "pressurei":"29.82","windchillm":"-999", "windchilli":"-999","heatindexm":"-9999", "heatindexi":"-9999","precipm":"-9999.00", "precipi":"-9999.00","conds":"Fog","icon":"fog","fog":"1","rain":"0","snow":"0","hail":"0","thunder":"0","tornado":"0","metar":"SPECI KMDW 290730Z 11003KT 1/2SM R31C/4500FT FG BKN003 OVC008 14/14 A2982 RMK AO2" },
		{
		"date": {
		"pretty": "2:44 AM CDT on May 29, 2011",
		"year": "2011",
		"mon": "05",
		"mday": "29",
		"hour": "02",
		"min": "44",
		"tzname": "America/Chicago"
		},
		"utcdate": {
		"pretty": "7:44 AM GMT on May 29, 2011",
		"year": "2011",
		"mon": "05",
		"mday": "29",
		"hour": "07",
		"min": "44",
		"tzname": "UTC"
		},
		"tempm":"14.0", "tempi":"57.2","dewptm":"14.0", "dewpti":"57.2","hum":"100","wspdm":"0.0", "wspdi":"0.0","wgustm":"-9999.0", "wgusti":"-9999.0","wdird":"0","wdire":"North","vism":"1.2", "visi":"0.8","pressurem":"1009.7", "pressurei":"29.82","windchillm":"-999", "windchilli":"-999","heatindexm":"-9999", "heatindexi":"-9999","precipm":"-9999.00", "precipi":"-9999.00","conds":"Overcast","icon":"cloudy","fog":"0","rain":"0","snow":"0","hail":"0","thunder":"0","tornado":"0","metar":"SPECI KMDW 290744Z 00000KT 3/4SM R31C/5500FT BR SCT003 OVC008 14/14 A2982 RMK AO2" },
		{
		"date": {
		"pretty": "2:51 AM CDT on May 29, 2011",
		"year": "2011",
		"mon": "05",
		"mday": "29",
		"hour": "02",
		"min": "51",
		"tzname": "America/Chicago"
		},
		"utcdate": {
		"pretty": "7:51 AM GMT on May 29, 2011",
		"year": "2011",
		"mon": "05",
		"mday": "29",
		"hour": "07",
		"min": "51",
		"tzname": "UTC"
		},
		"tempm":"14.4", "tempi":"57.9","dewptm":"13.9", "dewpti":"57.0","hum":"97","wspdm":"0.0", "wspdi":"0.0","wgustm":"-9999.0", "wgusti":"-9999.0","wdird":"0","wdire":"North","vism":"1.6", "visi":"1.0","pressurem":"1009.5", "pressurei":"29.81","windchillm":"-999", "windchilli":"-999","heatindexm":"-9999", "heatindexi":"-9999","precipm":"-9999.00", "precipi":"-9999.00","conds":"Overcast","icon":"cloudy","fog":"0","rain":"0","snow":"0","hail":"0","thunder":"0","tornado":"0","metar":"METAR KMDW 290751Z 00000KT 1SM R31C/6000FT BR SCT001 OVC008 14/14 A2982 RMK AO2 SLP095 VIS 3/4V1 T01440139" },
		{
		"date": {
		"pretty": "3:06 AM CDT on May 29, 2011",
		"year": "2011",
		"mon": "05",
		"mday": "29",
		"hour": "03",
		"min": "06",
		"tzname": "America/Chicago"
		},
		"utcdate": {
		"pretty": "8:06 AM GMT on May 29, 2011",
		"year": "2011",
		"mon": "05",
		"mday": "29",
		"hour": "08",
		"min": "06",
		"tzname": "UTC"
		},
		"tempm":"14.0", "tempi":"57.2","dewptm":"14.0", "dewpti":"57.2","hum":"100","wspdm":"0.0", "wspdi":"0.0","wgustm":"-9999.0", "wgusti":"-9999.0","wdird":"0","wdire":"North","vism":"3.2", "visi":"2.0","pressurem":"1009.7", "pressurei":"29.82","windchillm":"-999", "windchilli":"-999","heatindexm":"-9999", "heatindexi":"-9999","precipm":"-9999.00", "precipi":"-9999.00","conds":"Overcast","icon":"cloudy","fog":"0","rain":"0","snow":"0","hail":"0","thunder":"0","tornado":"0","metar":"SPECI KMDW 290806Z 00000KT 2SM BR FEW001 OVC008 14/14 A2982 RMK AO2" },
		{
		"date": {
		"pretty": "3:18 AM CDT on May 29, 2011",
		"year": "2011",
		"mon": "05",
		"mday": "29",
		"hour": "03",
		"min": "18",
		"tzname": "America/Chicago"
		},
		"utcdate": {
		"pretty": "8:18 AM GMT on May 29, 2011",
		"year": "2011",
		"mon": "05",
		"mday": "29",
		"hour": "08",
		"min": "18",
		"tzname": "UTC"
		},
		"tempm":"14.0", "tempi":"57.2","dewptm":"14.0", "dewpti":"57.2","hum":"100","wspdm":"0.0", "wspdi":"0.0","wgustm":"-9999.0", "wgusti":"-9999.0","wdird":"0","wdire":"North","vism":"4.8", "visi":"3.0","pressurem":"1009.7", "pressurei":"29.82","windchillm":"-999", "windchilli":"-999","heatindexm":"-9999", "heatindexi":"-9999","precipm":"-9999.00", "precipi":"-9999.00","conds":"Overcast","icon":"cloudy","fog":"0","rain":"0","snow":"0","hail":"0","thunder":"0","tornado":"0","metar":"SPECI KMDW 290818Z 00000KT 3SM BR FEW001 OVC008 14/14 A2982 RMK AO2" },
		{
		"date": {
		"pretty": "3:51 AM CDT on May 29, 2011",
		"year": "2011",
		"mon": "05",
		"mday": "29",
		"hour": "03",
		"min": "51",
		"tzname": "America/Chicago"
		},
		"utcdate": {
		"pretty": "8:51 AM GMT on May 29, 2011",
		"year": "2011",
		"mon": "05",
		"mday": "29",
		"hour": "08",
		"min": "51",
		"tzname": "UTC"
		},
		"tempm":"14.4", "tempi":"57.9","dewptm":"13.9", "dewpti":"57.0","hum":"97","wspdm":"0.0", "wspdi":"0.0","wgustm":"-9999.0", "wgusti":"-9999.0","wdird":"0","wdire":"North","vism":"4.8", "visi":"3.0","pressurem":"1009.4", "pressurei":"29.81","windchillm":"-999", "windchilli":"-999","heatindexm":"-9999", "heatindexi":"-9999","precipm":"-9999.00", "precipi":"-9999.00","conds":"Overcast","icon":"cloudy","fog":"0","rain":"0","snow":"0","hail":"0","thunder":"0","tornado":"0","metar":"METAR KMDW 290851Z 00000KT 3SM BR OVC006 14/14 A2981 RMK AO2 SLP094 T01440139 56003" },
		{
		"date": {
		"pretty": "4:30 AM CDT on May 29, 2011",
		"year": "2011",
		"mon": "05",
		"mday": "29",
		"hour": "04",
		"min": "30",
		"tzname": "America/Chicago"
		},
		"utcdate": {
		"pretty": "9:30 AM GMT on May 29, 2011",
		"year": "2011",
		"mon": "05",
		"mday": "29",
		"hour": "09",
		"min": "30",
		"tzname": "UTC"
		},
		"tempm":"14.0", "tempi":"57.2","dewptm":"14.0", "dewpti":"57.2","hum":"100","wspdm":"0.0", "wspdi":"0.0","wgustm":"-9999.0", "wgusti":"-9999.0","wdird":"0","wdire":"North","vism":"3.2", "visi":"2.0","pressurem":"1009.4", "pressurei":"29.81","windchillm":"-999", "windchilli":"-999","heatindexm":"-9999", "heatindexi":"-9999","precipm":"-9999.00", "precipi":"-9999.00","conds":"Overcast","icon":"cloudy","fog":"0","rain":"0","snow":"0","hail":"0","thunder":"0","tornado":"0","metar":"SPECI KMDW 290930Z 00000KT 2SM BR BKN002 OVC006 14/14 A2981 RMK AO2" },
		{
		"date": {
		"pretty": "4:41 AM CDT on May 29, 2011",
		"year": "2011",
		"mon": "05",
		"mday": "29",
		"hour": "04",
		"min": "41",
		"tzname": "America/Chicago"
		},
		"utcdate": {
		"pretty": "9:41 AM GMT on May 29, 2011",
		"year": "2011",
		"mon": "05",
		"mday": "29",
		"hour": "09",
		"min": "41",
		"tzname": "UTC"
		},
		"tempm":"14.0", "tempi":"57.2","dewptm":"14.0", "dewpti":"57.2","hum":"100","wspdm":"0.0", "wspdi":"0.0","wgustm":"-9999.0", "wgusti":"-9999.0","wdird":"0","wdire":"North","vism":"1.6", "visi":"1.0","pressurem":"1009.4", "pressurei":"29.81","windchillm":"-999", "windchilli":"-999","heatindexm":"-9999", "heatindexi":"-9999","precipm":"-9999.00", "precipi":"-9999.00","conds":"Overcast","icon":"cloudy","fog":"0","rain":"0","snow":"0","hail":"0","thunder":"0","tornado":"0","metar":"SPECI KMDW 290941Z 00000KT 1SM R31C/P6000FT BR OVC002 14/14 A2981 RMK AO2" },
		{
		"date": {
		"pretty": "4:51 AM CDT on May 29, 2011",
		"year": "2011",
		"mon": "05",
		"mday": "29",
		"hour": "04",
		"min": "51",
		"tzname": "America/Chicago"
		},
		"utcdate": {
		"pretty": "9:51 AM GMT on May 29, 2011",
		"year": "2011",
		"mon": "05",
		"mday": "29",
		"hour": "09",
		"min": "51",
		"tzname": "UTC"
		},
		"tempm":"14.4", "tempi":"57.9","dewptm":"14.4", "dewpti":"57.9","hum":"100","wspdm":"0.0", "wspdi":"0.0","wgustm":"-9999.0", "wgusti":"-9999.0","wdird":"0","wdire":"North","vism":"1.6", "visi":"1.0","pressurem":"1009.2", "pressurei":"29.81","windchillm":"-999", "windchilli":"-999","heatindexm":"-9999", "heatindexi":"-9999","precipm":"-9999.00", "precipi":"-9999.00","conds":"Overcast","icon":"cloudy","fog":"0","rain":"0","snow":"0","hail":"0","thunder":"0","tornado":"0","metar":"METAR KMDW 290951Z 00000KT 1SM R31C/P6000FT BR OVC002 14/14 A2981 RMK AO2 SLP092 T01440144" },
		{
		"date": {
		"pretty": "5:37 AM CDT on May 29, 2011",
		"year": "2011",
		"mon": "05",
		"mday": "29",
		"hour": "05",
		"min": "37",
		"tzname": "America/Chicago"
		},
		"utcdate": {
		"pretty": "10:37 AM GMT on May 29, 2011",
		"year": "2011",
		"mon": "05",
		"mday": "29",
		"hour": "10",
		"min": "37",
		"tzname": "UTC"
		},
		"tempm":"15.0", "tempi":"59.0","dewptm":"14.0", "dewpti":"57.2","hum":"94","wspdm":"0.0", "wspdi":"0.0","wgustm":"-9999.0", "wgusti":"-9999.0","wdird":"0","wdire":"North","vism":"1.2", "visi":"0.8","pressurem":"1009.7", "pressurei":"29.82","windchillm":"-999", "windchilli":"-999","heatindexm":"-9999", "heatindexi":"-9999","precipm":"-9999.00", "precipi":"-9999.00","conds":"Overcast","icon":"cloudy","fog":"0","rain":"0","snow":"0","hail":"0","thunder":"0","tornado":"0","metar":"SPECI KMDW 291037Z 00000KT 3/4SM R31C/5000FT BR OVC002 15/14 A2982 RMK AO2" },
		{
		"date": {
		"pretty": "5:51 AM CDT on May 29, 2011",
		"year": "2011",
		"mon": "05",
		"mday": "29",
		"hour": "05",
		"min": "51",
		"tzname": "America/Chicago"
		},
		"utcdate": {
		"pretty": "10:51 AM GMT on May 29, 2011",
		"year": "2011",
		"mon": "05",
		"mday": "29",
		"hour": "10",
		"min": "51",
		"tzname": "UTC"
		},
		"tempm":"15.0", "tempi":"59.0","dewptm":"14.4", "dewpti":"57.9","hum":"96","wspdm":"0.0", "wspdi":"0.0","wgustm":"-9999.0", "wgusti":"-9999.0","wdird":"0","wdire":"North","vism":"0.4", "visi":"0.2","pressurem":"1010.1", "pressurei":"29.83","windchillm":"-999", "windchilli":"-999","heatindexm":"-9999", "heatindexi":"-9999","precipm":"-9999.00", "precipi":"-9999.00","conds":"Fog","icon":"fog","fog":"1","rain":"0","snow":"0","hail":"0","thunder":"0","tornado":"0","metar":"METAR KMDW 291051Z 00000KT 1/4SM R31C/3000FT FG VV002 15/14 A2983 RMK AO2 SLP101 VIS 1/4V1/2 T01500144" },
		{
		"date": {
		"pretty": "6:51 AM CDT on May 29, 2011",
		"year": "2011",
		"mon": "05",
		"mday": "29",
		"hour": "06",
		"min": "51",
		"tzname": "America/Chicago"
		},
		"utcdate": {
		"pretty": "11:51 AM GMT on May 29, 2011",
		"year": "2011",
		"mon": "05",
		"mday": "29",
		"hour": "11",
		"min": "51",
		"tzname": "UTC"
		},
		"tempm":"15.6", "tempi":"60.1","dewptm":"15.6", "dewpti":"60.1","hum":"100","wspdm":"0.0", "wspdi":"0.0","wgustm":"-9999.0", "wgusti":"-9999.0","wdird":"0","wdire":"North","vism":"0.4", "visi":"0.2","pressurem":"1011.1", "pressurei":"29.86","windchillm":"-999", "windchilli":"-999","heatindexm":"-9999", "heatindexi":"-9999","precipm":"-9999.00", "precipi":"-9999.00","conds":"Fog","icon":"fog","fog":"1","rain":"0","snow":"0","hail":"0","thunder":"0","tornado":"0","metar":"METAR KMDW 291151Z 00000KT 1/4SM R31C/4000FT FG VV002 16/16 A2986 RMK AO2 SLP111 70023 T01560156 10156 20139 53017" },
		{
		"date": {
		"pretty": "7:14 AM CDT on May 29, 2011",
		"year": "2011",
		"mon": "05",
		"mday": "29",
		"hour": "07",
		"min": "14",
		"tzname": "America/Chicago"
		},
		"utcdate": {
		"pretty": "12:14 PM GMT on May 29, 2011",
		"year": "2011",
		"mon": "05",
		"mday": "29",
		"hour": "12",
		"min": "14",
		"tzname": "UTC"
		},
		"tempm":"16.0", "tempi":"60.8","dewptm":"16.0", "dewpti":"60.8","hum":"100","wspdm":"7.4", "wspdi":"4.6","wgustm":"-9999.0", "wgusti":"-9999.0","wdird":"40","wdire":"NE","vism":"0.4", "visi":"0.2","pressurem":"1010.7", "pressurei":"29.85","windchillm":"-999", "windchilli":"-999","heatindexm":"-9999", "heatindexi":"-9999","precipm":"-9999.00", "precipi":"-9999.00","conds":"Fog","icon":"fog","fog":"1","rain":"0","snow":"0","hail":"0","thunder":"0","tornado":"0","metar":"SPECI KMDW 291214Z 04004KT M1/4SM R31C/1600V2000FT FG VV001 16/16 A2985 RMK AO2" },
		{
		"date": {
		"pretty": "7:51 AM CDT on May 29, 2011",
		"year": "2011",
		"mon": "05",
		"mday": "29",
		"hour": "07",
		"min": "51",
		"tzname": "America/Chicago"
		},
		"utcdate": {
		"pretty": "12:51 PM GMT on May 29, 2011",
		"year": "2011",
		"mon": "05",
		"mday": "29",
		"hour": "12",
		"min": "51",
		"tzname": "UTC"
		},
		"tempm":"16.1", "tempi":"61.0","dewptm":"16.1", "dewpti":"61.0","hum":"100","wspdm":"5.6", "wspdi":"3.5","wgustm":"-9999.0", "wgusti":"-9999.0","wdird":"90","wdire":"East","vism":"0.4", "visi":"0.2","pressurem":"1010.7", "pressurei":"29.85","windchillm":"-999", "windchilli":"-999","heatindexm":"-9999", "heatindexi":"-9999","precipm":"-9999.00", "precipi":"-9999.00","conds":"Fog","icon":"fog","fog":"1","rain":"0","snow":"0","hail":"0","thunder":"0","tornado":"0","metar":"METAR KMDW 291251Z 09003KT M1/4SM R31C/1400V2000FT FG VV001 16/16 A2985 RMK AO2 SLP107 T01610161" },
		{
		"date": {
		"pretty": "8:26 AM CDT on May 29, 2011",
		"year": "2011",
		"mon": "05",
		"mday": "29",
		"hour": "08",
		"min": "26",
		"tzname": "America/Chicago"
		},
		"utcdate": {
		"pretty": "1:26 PM GMT on May 29, 2011",
		"year": "2011",
		"mon": "05",
		"mday": "29",
		"hour": "13",
		"min": "26",
		"tzname": "UTC"
		},
		"tempm":"16.0", "tempi":"60.8","dewptm":"16.0", "dewpti":"60.8","hum":"100","wspdm":"5.6", "wspdi":"3.5","wgustm":"-9999.0", "wgusti":"-9999.0","wdird":"80","wdire":"East","vism":"0.4", "visi":"0.2","pressurem":"1011.4", "pressurei":"29.87","windchillm":"-999", "windchilli":"-999","heatindexm":"-9999", "heatindexi":"-9999","precipm":"-9999.00", "precipi":"-9999.00","conds":"Fog","icon":"fog","fog":"1","rain":"0","snow":"0","hail":"0","thunder":"0","tornado":"0","metar":"SPECI KMDW 291326Z 08003KT 1/4SM R31C/2400V3500FT FG VV001 16/16 A2987 RMK AO2" },
		{
		"date": {
		"pretty": "8:51 AM CDT on May 29, 2011",
		"year": "2011",
		"mon": "05",
		"mday": "29",
		"hour": "08",
		"min": "51",
		"tzname": "America/Chicago"
		},
		"utcdate": {
		"pretty": "1:51 PM GMT on May 29, 2011",
		"year": "2011",
		"mon": "05",
		"mday": "29",
		"hour": "13",
		"min": "51",
		"tzname": "UTC"
		},
		"tempm":"16.1", "tempi":"61.0","dewptm":"16.1", "dewpti":"61.0","hum":"100","wspdm":"11.1", "wspdi":"6.9","wgustm":"-9999.0", "wgusti":"-9999.0","wdird":"50","wdire":"NE","vism":"1.2", "visi":"0.8","pressurem":"1011.0", "pressurei":"29.86","windchillm":"-999", "windchilli":"-999","heatindexm":"-9999", "heatindexi":"-9999","precipm":"-9999.00", "precipi":"-9999.00","conds":"Mist","icon":"hazy","fog":"0","rain":"0","snow":"0","hail":"0","thunder":"0","tornado":"0","metar":"METAR KMDW 291351Z 05006KT 3/4SM R31C/P6000FT BR VV001 16/16 A2986 RMK AO2 SLP110 T01610161" },
		{
		"date": {
		"pretty": "9:06 AM CDT on May 29, 2011",
		"year": "2011",
		"mon": "05",
		"mday": "29",
		"hour": "09",
		"min": "06",
		"tzname": "America/Chicago"
		},
		"utcdate": {
		"pretty": "2:06 PM GMT on May 29, 2011",
		"year": "2011",
		"mon": "05",
		"mday": "29",
		"hour": "14",
		"min": "06",
		"tzname": "UTC"
		},
		"tempm":"15.0", "tempi":"59.0","dewptm":"15.0", "dewpti":"59.0","hum":"100","wspdm":"11.1", "wspdi":"6.9","wgustm":"-9999.0", "wgusti":"-9999.0","wdird":"40","wdire":"NE","vism":"1.6", "visi":"1.0","pressurem":"1011.7", "pressurei":"29.88","windchillm":"-999", "windchilli":"-999","heatindexm":"-9999", "heatindexi":"-9999","precipm":"-9999.00", "precipi":"-9999.00","conds":"Overcast","icon":"cloudy","fog":"0","rain":"0","snow":"0","hail":"0","thunder":"0","tornado":"0","metar":"SPECI KMDW 291406Z 04006KT 1SM R31C/P6000FT BR OVC003 15/15 A2988 RMK AO2" },
		{
		"date": {
		"pretty": "9:30 AM CDT on May 29, 2011",
		"year": "2011",
		"mon": "05",
		"mday": "29",
		"hour": "09",
		"min": "30",
		"tzname": "America/Chicago"
		},
		"utcdate": {
		"pretty": "2:30 PM GMT on May 29, 2011",
		"year": "2011",
		"mon": "05",
		"mday": "29",
		"hour": "14",
		"min": "30",
		"tzname": "UTC"
		},
		"tempm":"15.0", "tempi":"59.0","dewptm":"14.0", "dewpti":"57.2","hum":"94","wspdm":"11.1", "wspdi":"6.9","wgustm":"-9999.0", "wgusti":"-9999.0","wdird":"50","wdire":"NE","vism":"3.2", "visi":"2.0","pressurem":"1011.1", "pressurei":"29.86","windchillm":"-999", "windchilli":"-999","heatindexm":"-9999", "heatindexi":"-9999","precipm":"-9999.00", "precipi":"-9999.00","conds":"Overcast","icon":"cloudy","fog":"0","rain":"0","snow":"0","hail":"0","thunder":"0","tornado":"0","metar":"SPECI KMDW 291430Z 05006KT 2SM BR OVC003 15/14 A2986 RMK AO2" },
		{
		"date": {
		"pretty": "9:51 AM CDT on May 29, 2011",
		"year": "2011",
		"mon": "05",
		"mday": "29",
		"hour": "09",
		"min": "51",
		"tzname": "America/Chicago"
		},
		"utcdate": {
		"pretty": "2:51 PM GMT on May 29, 2011",
		"year": "2011",
		"mon": "05",
		"mday": "29",
		"hour": "14",
		"min": "51",
		"tzname": "UTC"
		},
		"tempm":"15.6", "tempi":"60.1","dewptm":"14.4", "dewpti":"57.9","hum":"93","wspdm":"14.8", "wspdi":"9.2","wgustm":"-9999.0", "wgusti":"-9999.0","wdird":"50","wdire":"NE","vism":"2.4", "visi":"1.5","pressurem":"1011.2", "pressurei":"29.86","windchillm":"-999", "windchilli":"-999","heatindexm":"-9999", "heatindexi":"-9999","precipm":"0.0", "precipi":"0.00","conds":"Overcast","icon":"cloudy","fog":"0","rain":"0","snow":"0","hail":"0","thunder":"0","tornado":"0","metar":"METAR KMDW 291451Z 05008KT 1 1/2SM BR OVC003 16/14 A2987 RMK AO2 RAB40E50 SLP112 P0000 60000 T01560144 53001" },
		{
		"date": {
		"pretty": "10:34 AM CDT on May 29, 2011",
		"year": "2011",
		"mon": "05",
		"mday": "29",
		"hour": "10",
		"min": "34",
		"tzname": "America/Chicago"
		},
		"utcdate": {
		"pretty": "3:34 PM GMT on May 29, 2011",
		"year": "2011",
		"mon": "05",
		"mday": "29",
		"hour": "15",
		"min": "34",
		"tzname": "UTC"
		},
		"tempm":"16.0", "tempi":"60.8","dewptm":"15.0", "dewpti":"59.0","hum":"94","wspdm":"13.0", "wspdi":"8.1","wgustm":"-9999.0", "wgusti":"-9999.0","wdird":"80","wdire":"East","vism":"0.8", "visi":"0.5","pressurem":"1011.1", "pressurei":"29.86","windchillm":"-999", "windchilli":"-999","heatindexm":"-9999", "heatindexi":"-9999","precipm":"0.0", "precipi":"0.00","conds":"Fog","icon":"fog","fog":"1","rain":"0","snow":"0","hail":"0","thunder":"0","tornado":"0","metar":"SPECI KMDW 291534Z 08007KT 1/2SM R31C/3500V5000FT FG BKN001 OVC004 16/15 A2986 RMK AO2 RAB03E17 P0000" },
		{
		"date": {
		"pretty": "10:51 AM CDT on May 29, 2011",
		"year": "2011",
		"mon": "05",
		"mday": "29",
		"hour": "10",
		"min": "51",
		"tzname": "America/Chicago"
		},
		"utcdate": {
		"pretty": "3:51 PM GMT on May 29, 2011",
		"year": "2011",
		"mon": "05",
		"mday": "29",
		"hour": "15",
		"min": "51",
		"tzname": "UTC"
		},
		"tempm":"14.4", "tempi":"57.9","dewptm":"14.4", "dewpti":"57.9","hum":"100","wspdm":"9.3", "wspdi":"5.8","wgustm":"-9999.0", "wgusti":"-9999.0","wdird":"40","wdire":"NE","vism":"1.2", "visi":"0.8","pressurem":"1012.0", "pressurei":"29.89","windchillm":"-999", "windchilli":"-999","heatindexm":"-9999", "heatindexi":"-9999","precipm":"6.1", "precipi":"0.24","conds":"Rain","icon":"rain","fog":"0","rain":"1","snow":"0","hail":"0","thunder":"0","tornado":"0","metar":"METAR KMDW 291551Z 04005KT 3/4SM R31C/P6000FT RA BR VV001 14/14 A2989 RMK AO2 RAB03E17B42 PRESRR SLP120 P0024 T01440144" },
		{
		"date": {
		"pretty": "11:02 AM CDT on May 29, 2011",
		"year": "2011",
		"mon": "05",
		"mday": "29",
		"hour": "11",
		"min": "02",
		"tzname": "America/Chicago"
		},
		"utcdate": {
		"pretty": "4:02 PM GMT on May 29, 2011",
		"year": "2011",
		"mon": "05",
		"mday": "29",
		"hour": "16",
		"min": "02",
		"tzname": "UTC"
		},
		"tempm":"14.0", "tempi":"57.2","dewptm":"14.0", "dewpti":"57.2","hum":"100","wspdm":"9.3", "wspdi":"5.8","wgustm":"-9999.0", "wgusti":"-9999.0","wdird":"80","wdire":"East","vism":"1.2", "visi":"0.8","pressurem":"1012.1", "pressurei":"29.89","windchillm":"-999", "windchilli":"-999","heatindexm":"-9999", "heatindexi":"-9999","precipm":"0.0", "precipi":"0.00","conds":"Light Thunderstorms and Rain","icon":"tstorms","fog":"0","rain":"1","snow":"0","hail":"0","thunder":"1","tornado":"0","metar":"SPECI KMDW 291602Z COR 08005KT 3/4SM R31C/P6000FT -TSRA BR OVC003CB 14/14 A2989 RMK AO2 TSB02 OCNL LTGIC OHD TS OHD MOV NE P0000" },
		{
		"date": {
		"pretty": "11:29 AM CDT on May 29, 2011",
		"year": "2011",
		"mon": "05",
		"mday": "29",
		"hour": "11",
		"min": "29",
		"tzname": "America/Chicago"
		},
		"utcdate": {
		"pretty": "4:29 PM GMT on May 29, 2011",
		"year": "2011",
		"mon": "05",
		"mday": "29",
		"hour": "16",
		"min": "29",
		"tzname": "UTC"
		},
		"tempm":"14.0", "tempi":"57.2","dewptm":"14.0", "dewpti":"57.2","hum":"100","wspdm":"14.8", "wspdi":"9.2","wgustm":"-9999.0", "wgusti":"-9999.0","wdird":"80","wdire":"East","vism":"2.8", "visi":"1.8","pressurem":"1012.1", "pressurei":"29.89","windchillm":"-999", "windchilli":"-999","heatindexm":"-9999", "heatindexi":"-9999","precipm":"0.3", "precipi":"0.01","conds":"Light Thunderstorms and Rain","icon":"tstorms","fog":"0","rain":"1","snow":"0","hail":"0","thunder":"1","tornado":"0","metar":"SPECI KMDW 291629Z 08008KT 1 3/4SM -TSRA OVC003CB 14/14 A2989 RMK AO2 TSB02 FRQ LTGIC VC W OHD VC E TS VC W OHD VC E MOV NE P0001 $" },
		{
		"date": {
		"pretty": "11:51 AM CDT on May 29, 2011",
		"year": "2011",
		"mon": "05",
		"mday": "29",
		"hour": "11",
		"min": "51",
		"tzname": "America/Chicago"
		},
		"utcdate": {
		"pretty": "4:51 PM GMT on May 29, 2011",
		"year": "2011",
		"mon": "05",
		"mday": "29",
		"hour": "16",
		"min": "51",
		"tzname": "UTC"
		},
		"tempm":"14.4", "tempi":"57.9","dewptm":"13.9", "dewpti":"57.0","hum":"97","wspdm":"9.3", "wspdi":"5.8","wgustm":"-9999.0", "wgusti":"-9999.0","wdird":"60","wdire":"ENE","vism":"2.4", "visi":"1.5","pressurem":"1012.2", "pressurei":"29.89","windchillm":"-999", "windchilli":"-999","heatindexm":"-9999", "heatindexi":"-9999","precipm":"0.3", "precipi":"0.01","conds":"Overcast","icon":"cloudy","fog":"0","rain":"0","snow":"0","hail":"0","thunder":"0","tornado":"0","metar":"METAR KMDW 291651Z 06005KT 1 1/2SM BR OVC003 14/14 A2990 RMK AO2 TSB02E47RAE47 SLP122 FRQ LTGIC DSNT NW N E DSNT TS NW N NE MOV NE P0001 T01440139 $" },
		{
		"date": {
		"pretty": "12:24 PM CDT on May 29, 2011",
		"year": "2011",
		"mon": "05",
		"mday": "29",
		"hour": "12",
		"min": "24",
		"tzname": "America/Chicago"
		},
		"utcdate": {
		"pretty": "5:24 PM GMT on May 29, 2011",
		"year": "2011",
		"mon": "05",
		"mday": "29",
		"hour": "17",
		"min": "24",
		"tzname": "UTC"
		},
		"tempm":"14.0", "tempi":"57.2","dewptm":"14.0", "dewpti":"57.2","hum":"100","wspdm":"16.7", "wspdi":"10.4","wgustm":"33.3", "wgusti":"20.7","wdird":"340","wdire":"NNW","vism":"6.4", "visi":"4.0","pressurem":"1013.4", "pressurei":"29.93","windchillm":"-999", "windchilli":"-999","heatindexm":"-9999", "heatindexi":"-9999","precipm":"-9999.00", "precipi":"-9999.00","conds":"Overcast","icon":"cloudy","fog":"0","rain":"0","snow":"0","hail":"0","thunder":"1","tornado":"0","metar":"SPECI KMDW 291724Z 34009G18KT 310V030 4SM TS BR OVC003CB 14/14 A2993 RMK AO2 TSB24 FRQ LTGIC OHD TS OHD MOV NE $" },
		{
		"date": {
		"pretty": "12:37 PM CDT on May 29, 2011",
		"year": "2011",
		"mon": "05",
		"mday": "29",
		"hour": "12",
		"min": "37",
		"tzname": "America/Chicago"
		},
		"utcdate": {
		"pretty": "5:37 PM GMT on May 29, 2011",
		"year": "2011",
		"mon": "05",
		"mday": "29",
		"hour": "17",
		"min": "37",
		"tzname": "UTC"
		},
		"tempm":"16.0", "tempi":"60.8","dewptm":"14.0", "dewpti":"57.2","hum":"88","wspdm":"16.7", "wspdi":"10.4","wgustm":"-9999.0", "wgusti":"-9999.0","wdird":"70","wdire":"ENE","vism":"12.9", "visi":"8.0","pressurem":"1012.4", "pressurei":"29.90","windchillm":"-999", "windchilli":"-999","heatindexm":"-9999", "heatindexi":"-9999","precipm":"-9999.00", "precipi":"-9999.00","conds":"Overcast","icon":"cloudy","fog":"0","rain":"0","snow":"0","hail":"0","thunder":"0","tornado":"0","metar":"SPECI KMDW 291737Z 07009KT 8SM SCT003 OVC014 16/14 A2990 RMK AO2 TSB24E36 PRESFR FRQ LTGIC DSNT NW N CB DSNT NW N MOV NE $" },
		{
		"date": {
		"pretty": "12:51 PM CDT on May 29, 2011",
		"year": "2011",
		"mon": "05",
		"mday": "29",
		"hour": "12",
		"min": "51",
		"tzname": "America/Chicago"
		},
		"utcdate": {
		"pretty": "5:51 PM GMT on May 29, 2011",
		"year": "2011",
		"mon": "05",
		"mday": "29",
		"hour": "17",
		"min": "51",
		"tzname": "UTC"
		},
		"tempm":"15.6", "tempi":"60.1","dewptm":"14.4", "dewpti":"57.9","hum":"93","wspdm":"14.8", "wspdi":"9.2","wgustm":"-9999.0", "wgusti":"-9999.0","wdird":"70","wdire":"ENE","vism":"16.1", "visi":"10.0","pressurem":"1012.1", "pressurei":"29.89","windchillm":"-999", "windchilli":"-999","heatindexm":"-9999", "heatindexi":"-9999","precipm":"-9999.00", "precipi":"-9999.00","conds":"Overcast","icon":"cloudy","fog":"0","rain":"0","snow":"0","hail":"0","thunder":"0","tornado":"0","metar":"METAR KMDW 291751Z 07008KT 10SM FEW003 BKN016 OVC021 16/14 A2989 RMK AO2 TSB24E36 SLP121 FRQ LTGIC DSNT N CB DSNT NW N MOV NE 60025 T01560144 10161 20144 50009 $" },
		{
		"date": {
		"pretty": "1:14 PM CDT on May 29, 2011",
		"year": "2011",
		"mon": "05",
		"mday": "29",
		"hour": "13",
		"min": "14",
		"tzname": "America/Chicago"
		},
		"utcdate": {
		"pretty": "6:14 PM GMT on May 29, 2011",
		"year": "2011",
		"mon": "05",
		"mday": "29",
		"hour": "18",
		"min": "14",
		"tzname": "UTC"
		},
		"tempm":"16.0", "tempi":"60.8","dewptm":"15.0", "dewpti":"59.0","hum":"94","wspdm":"0.0", "wspdi":"0.0","wgustm":"-9999.0", "wgusti":"-9999.0","wdird":"0","wdire":"North","vism":"12.9", "visi":"8.0","pressurem":"1013.1", "pressurei":"29.92","windchillm":"-999", "windchilli":"-999","heatindexm":"-9999", "heatindexi":"-9999","precipm":"-9999.00", "precipi":"-9999.00","conds":"Thunderstorm","icon":"tstorms","fog":"0","rain":"0","snow":"0","hail":"0","thunder":"1","tornado":"0","metar":"SPECI KMDW 291814Z 00000KT 8SM TS OVC018CB 16/15 A2992 RMK AO2 TSB13 OCNL LTGICCG OHD TS OHD MOV NE $" },
		{
		"date": {
		"pretty": "1:24 PM CDT on May 29, 2011",
		"year": "2011",
		"mon": "05",
		"mday": "29",
		"hour": "13",
		"min": "24",
		"tzname": "America/Chicago"
		},
		"utcdate": {
		"pretty": "6:24 PM GMT on May 29, 2011",
		"year": "2011",
		"mon": "05",
		"mday": "29",
		"hour": "18",
		"min": "24",
		"tzname": "UTC"
		},
		"tempm":"16.0", "tempi":"60.8","dewptm":"15.0", "dewpti":"59.0","hum":"94","wspdm":"22.2", "wspdi":"13.8","wgustm":"29.6", "wgusti":"18.4","wdird":"230","wdire":"SW","vism":"1.6", "visi":"1.0","pressurem":"1015.5", "pressurei":"29.99","windchillm":"-999", "windchilli":"-999","heatindexm":"-9999", "heatindexi":"-9999","precipm":"4.8", "precipi":"0.19","conds":"Heavy Thunderstorms and Rain","icon":"tstorms","fog":"0","rain":"1","snow":"0","hail":"0","thunder":"1","tornado":"0","metar":"SPECI KMDW 291824Z 23012G16KT 1SM R31C/5500FT +TSRA BR OVC018CB 16/15 A2999 RMK AO2 TSB13RAB18 PRESRR CONT LTGICCG OHD TS OHD MOV NE P0019 $" },
		{
		"date": {
		"pretty": "1:32 PM CDT on May 29, 2011",
		"year": "2011",
		"mon": "05",
		"mday": "29",
		"hour": "13",
		"min": "32",
		"tzname": "America/Chicago"
		},
		"utcdate": {
		"pretty": "6:32 PM GMT on May 29, 2011",
		"year": "2011",
		"mon": "05",
		"mday": "29",
		"hour": "18",
		"min": "32",
		"tzname": "UTC"
		},
		"tempm":"16.0", "tempi":"60.8","dewptm":"16.0", "dewpti":"60.8","hum":"100","wspdm":"24.1", "wspdi":"15.0","wgustm":"46.3", "wgusti":"28.8","wdird":"290","wdire":"WNW","vism":"0.8", "visi":"0.5","pressurem":"1017.5", "pressurei":"30.05","windchillm":"-999", "windchilli":"-999","heatindexm":"-9999", "heatindexi":"-9999","precipm":"11.2", "precipi":"0.44","conds":"Heavy Thunderstorms and Rain","icon":"tstorms","fog":"1","rain":"1","snow":"0","hail":"0","thunder":"1","tornado":"0","metar":"SPECI KMDW 291832Z 29013G25KT 1/2SM R31C/3000FT +TSRA FG FEW011 OVC018CB 16/16 A3005 RMK AO2 TSB13RAB18 PRESRR CONS LTGICCG OHD TS OHD MOV NE P0044 $" },
		{
		"date": {
		"pretty": "1:44 PM CDT on May 29, 2011",
		"year": "2011",
		"mon": "05",
		"mday": "29",
		"hour": "13",
		"min": "44",
		"tzname": "America/Chicago"
		},
		"utcdate": {
		"pretty": "6:44 PM GMT on May 29, 2011",
		"year": "2011",
		"mon": "05",
		"mday": "29",
		"hour": "18",
		"min": "44",
		"tzname": "UTC"
		},
		"tempm":"16.0", "tempi":"60.8","dewptm":"16.0", "dewpti":"60.8","hum":"100","wspdm":"16.7", "wspdi":"10.4","wgustm":"-9999.0", "wgusti":"-9999.0","wdird":"340","wdire":"NNW","vism":"3.2", "visi":"2.0","pressurem":"1016.1", "pressurei":"30.01","windchillm":"-999", "windchilli":"-999","heatindexm":"-9999", "heatindexi":"-9999","precipm":"14.2", "precipi":"0.56","conds":"Heavy Thunderstorms and Rain","icon":"tstorms","fog":"0","rain":"1","snow":"0","hail":"0","thunder":"1","tornado":"0","metar":"SPECI KMDW 291844Z 34009KT 2SM +TSRA BR SCT009 OVC020CB 16/16 A3001 RMK AO2 TSB13RAB18 CONS LTGICCG OHD TS OHD MOV NE P0056 $" },
		{
		"date": {
		"pretty": "1:51 PM CDT on May 29, 2011",
		"year": "2011",
		"mon": "05",
		"mday": "29",
		"hour": "13",
		"min": "51",
		"tzname": "America/Chicago"
		},
		"utcdate": {
		"pretty": "6:51 PM GMT on May 29, 2011",
		"year": "2011",
		"mon": "05",
		"mday": "29",
		"hour": "18",
		"min": "51",
		"tzname": "UTC"
		},
		"tempm":"16.1", "tempi":"61.0","dewptm":"16.1", "dewpti":"61.0","hum":"100","wspdm":"18.5", "wspdi":"11.5","wgustm":"-9999.0", "wgusti":"-9999.0","wdird":"330","wdire":"NNW","vism":"4.8", "visi":"3.0","pressurem":"1016.5", "pressurei":"30.02","windchillm":"-999", "windchilli":"-999","heatindexm":"-9999", "heatindexi":"-9999","precipm":"14.7", "precipi":"0.58","conds":"Thunderstorms and Rain","icon":"tstorms","fog":"0","rain":"1","snow":"0","hail":"0","thunder":"1","tornado":"0","metar":"METAR KMDW 291851Z 33010KT 3SM TSRA BR FEW009 BKN017CB OVC085 16/16 A3002 RMK AO2 TSB13RAB18 SLP165 CONS LTGICCG OHD TS OHD MOV NE P0058 T01610161 $" },
		{
		"date": {
		"pretty": "2:14 PM CDT on May 29, 2011",
		"year": "2011",
		"mon": "05",
		"mday": "29",
		"hour": "14",
		"min": "14",
		"tzname": "America/Chicago"
		},
		"utcdate": {
		"pretty": "7:14 PM GMT on May 29, 2011",
		"year": "2011",
		"mon": "05",
		"mday": "29",
		"hour": "19",
		"min": "14",
		"tzname": "UTC"
		},
		"tempm":"16.0", "tempi":"60.8","dewptm":"16.0", "dewpti":"60.8","hum":"100","wspdm":"11.1", "wspdi":"6.9","wgustm":"-9999.0", "wgusti":"-9999.0","wdird":"30","wdire":"NNE","vism":"16.1", "visi":"10.0","pressurem":"1014.8", "pressurei":"29.97","windchillm":"-999", "windchilli":"-999","heatindexm":"-9999", "heatindexi":"-9999","precipm":"1.0", "precipi":"0.04","conds":"Light Thunderstorms and Rain","icon":"tstorms","fog":"0","rain":"1","snow":"0","hail":"0","thunder":"1","tornado":"0","metar":"SPECI KMDW 291914Z COR 03006KT 10SM -TSRA FEW009 SCT017CB OVC055 16/16 A2997 RMK AO2 OCNL LTG OHD TS OHD MOV E P0004 $" },
		{
		"date": {
		"pretty": "2:31 PM CDT on May 29, 2011",
		"year": "2011",
		"mon": "05",
		"mday": "29",
		"hour": "14",
		"min": "31",
		"tzname": "America/Chicago"
		},
		"utcdate": {
		"pretty": "7:31 PM GMT on May 29, 2011",
		"year": "2011",
		"mon": "05",
		"mday": "29",
		"hour": "19",
		"min": "31",
		"tzname": "UTC"
		},
		"tempm":"17.0", "tempi":"62.6","dewptm":"16.0", "dewpti":"60.8","hum":"94","wspdm":"22.2", "wspdi":"13.8","wgustm":"-9999.0", "wgusti":"-9999.0","wdird":"40","wdire":"NE","vism":"16.1", "visi":"10.0","pressurem":"1012.8", "pressurei":"29.91","windchillm":"-999", "windchilli":"-999","heatindexm":"-9999", "heatindexi":"-9999","precipm":"1.8", "precipi":"0.07","conds":"Light Rain","icon":"rain","fog":"0","rain":"1","snow":"0","hail":"0","thunder":"0","tornado":"0","metar":"SPECI KMDW 291931Z 04012KT 10SM -RA FEW009 BKN036 BKN055 OVC200 17/16 A2991 RMK AO2 TSE30 PRESFR OCNL LTGICCC DSNT NE-E P0007 $" },
		{
		"date": {
		"pretty": "2:51 PM CDT on May 29, 2011",
		"year": "2011",
		"mon": "05",
		"mday": "29",
		"hour": "14",
		"min": "51",
		"tzname": "America/Chicago"
		},
		"utcdate": {
		"pretty": "7:51 PM GMT on May 29, 2011",
		"year": "2011",
		"mon": "05",
		"mday": "29",
		"hour": "19",
		"min": "51",
		"tzname": "UTC"
		},
		"tempm":"17.0", "tempi":"62.6","dewptm":"17.0", "dewpti":"62.6","hum":"100","wspdm":"27.8", "wspdi":"17.3","wgustm":"-9999.0", "wgusti":"-9999.0","wdird":"60","wdire":"ENE","vism":"16.1", "visi":"10.0","pressurem":"1009.7", "pressurei":"29.82","windchillm":"-999", "windchilli":"-999","heatindexm":"-9999", "heatindexi":"-9999","precipm":"-9999.00", "precipi":"-9999.00","conds":"Light Rain","icon":"rain","fog":"0","rain":"1","snow":"0","hail":"0","thunder":"0","tornado":"0","metar":"METAR KMDW 291951Z 06015KT 10SM -RA FEW009 BKN031 BKN055 OVC200 17/17 A2982" },
		{
		"date": {
		"pretty": "3:49 PM CDT on May 29, 2011",
		"year": "2011",
		"mon": "05",
		"mday": "29",
		"hour": "15",
		"min": "49",
		"tzname": "America/Chicago"
		},
		"utcdate": {
		"pretty": "8:49 PM GMT on May 29, 2011",
		"year": "2011",
		"mon": "05",
		"mday": "29",
		"hour": "20",
		"min": "49",
		"tzname": "UTC"
		},
		"tempm":"19.0", "tempi":"66.2","dewptm":"17.0", "dewpti":"62.6","hum":"88","wspdm":"24.1", "wspdi":"15.0","wgustm":"35.2", "wgusti":"21.9","wdird":"160","wdire":"SSE","vism":"16.1", "visi":"10.0","pressurem":"1009.7", "pressurei":"29.82","windchillm":"-999", "windchilli":"-999","heatindexm":"-9999", "heatindexi":"-9999","precipm":"0.3", "precipi":"0.01","conds":"Overcast","icon":"cloudy","fog":"0","rain":"0","snow":"0","hail":"0","thunder":"0","tornado":"0","metar":"SPECI KMDW 292049Z 16013G19KT 10SM FEW070 SCT150 BKN200 OVC250 19/17 A2982 RMK AO2 WSHFT 2029 RAE1958 SHRA DSNT E-SE P0001 $" },
		{
		"date": {
		"pretty": "3:51 PM CDT on May 29, 2011",
		"year": "2011",
		"mon": "05",
		"mday": "29",
		"hour": "15",
		"min": "51",
		"tzname": "America/Chicago"
		},
		"utcdate": {
		"pretty": "8:51 PM GMT on May 29, 2011",
		"year": "2011",
		"mon": "05",
		"mday": "29",
		"hour": "20",
		"min": "51",
		"tzname": "UTC"
		},
		"tempm":"19.4", "tempi":"66.9","dewptm":"16.7", "dewpti":"62.1","hum":"84","wspdm":"24.1", "wspdi":"15.0","wgustm":"35.2", "wgusti":"21.9","wdird":"170","wdire":"South","vism":"16.1", "visi":"10.0","pressurem":"1009.5", "pressurei":"29.81","windchillm":"-999", "windchilli":"-999","heatindexm":"-9999", "heatindexi":"-9999","precipm":"0.3", "precipi":"0.01","conds":"Overcast","icon":"cloudy","fog":"0","rain":"0","snow":"0","hail":"0","thunder":"0","tornado":"0","metar":"METAR KMDW 292051Z 17013G19KT 10SM FEW070 SCT150 BKN200 OVC250 19/17 A2982 RMK AO2 WSHFT 2029 RAE1958 PRESRR SLP095 SHRA DSNT E-SE P0001 60067 T01940167 55067 $" },
		{
		"date": {
		"pretty": "4:51 PM CDT on May 29, 2011",
		"year": "2011",
		"mon": "05",
		"mday": "29",
		"hour": "16",
		"min": "51",
		"tzname": "America/Chicago"
		},
		"utcdate": {
		"pretty": "9:51 PM GMT on May 29, 2011",
		"year": "2011",
		"mon": "05",
		"mday": "29",
		"hour": "21",
		"min": "51",
		"tzname": "UTC"
		},
		"tempm":"18.9", "tempi":"66.0","dewptm":"16.7", "dewpti":"62.1","hum":"87","wspdm":"22.2", "wspdi":"13.8","wgustm":"35.2", "wgusti":"21.9","wdird":"170","wdire":"South","vism":"16.1", "visi":"10.0","pressurem":"1010.8", "pressurei":"29.85","windchillm":"-999", "windchilli":"-999","heatindexm":"-9999", "heatindexi":"-9999","precipm":"-9999.00", "precipi":"-9999.00","conds":"Overcast","icon":"cloudy","fog":"0","rain":"0","snow":"0","hail":"0","thunder":"0","tornado":"0","metar":"METAR KMDW 292151Z 17012G19KT 10SM SCT150 BKN200 OVC250 19/17 A2986 RMK AO2 WSHFT 2038 SLP108 T01890167 $" },
		{
		"date": {
		"pretty": "5:51 PM CDT on May 29, 2011",
		"year": "2011",
		"mon": "05",
		"mday": "29",
		"hour": "17",
		"min": "51",
		"tzname": "America/Chicago"
		},
		"utcdate": {
		"pretty": "10:51 PM GMT on May 29, 2011",
		"year": "2011",
		"mon": "05",
		"mday": "29",
		"hour": "22",
		"min": "51",
		"tzname": "UTC"
		},
		"tempm":"20.6", "tempi":"69.1","dewptm":"17.2", "dewpti":"63.0","hum":"81","wspdm":"18.5", "wspdi":"11.5","wgustm":"-9999.0", "wgusti":"-9999.0","wdird":"170","wdire":"South","vism":"16.1", "visi":"10.0","pressurem":"1011.5", "pressurei":"29.87","windchillm":"-999", "windchilli":"-999","heatindexm":"-9999", "heatindexi":"-9999","precipm":"-9999.00", "precipi":"-9999.00","conds":"Overcast","icon":"cloudy","fog":"0","rain":"0","snow":"0","hail":"0","thunder":"0","tornado":"0","metar":"METAR KMDW 292251Z 17010KT 10SM FEW100 SCT150 OVC250 21/17 A2988 RMK AO2 SLP115 T02060172 $" },
		{
		"date": {
		"pretty": "6:51 PM CDT on May 29, 2011",
		"year": "2011",
		"mon": "05",
		"mday": "29",
		"hour": "18",
		"min": "51",
		"tzname": "America/Chicago"
		},
		"utcdate": {
		"pretty": "11:51 PM GMT on May 29, 2011",
		"year": "2011",
		"mon": "05",
		"mday": "29",
		"hour": "23",
		"min": "51",
		"tzname": "UTC"
		},
		"tempm":"21.7", "tempi":"71.1","dewptm":"16.7", "dewpti":"62.1","hum":"73","wspdm":"13.0", "wspdi":"8.1","wgustm":"-9999.0", "wgusti":"-9999.0","wdird":"160","wdire":"SSE","vism":"16.1", "visi":"10.0","pressurem":"1011.1", "pressurei":"29.86","windchillm":"-999", "windchilli":"-999","heatindexm":"-9999", "heatindexi":"-9999","precipm":"-9999.00", "precipi":"-9999.00","conds":"Overcast","icon":"cloudy","fog":"0","rain":"0","snow":"0","hail":"0","thunder":"0","tornado":"0","metar":"METAR KMDW 292351Z 16007KT 10SM FEW100 SCT150 OVC250 22/17 A2987 RMK AO2 SLP111 60067 T02170167 10217 20156 50017 $" },
		{
		"date": {
		"pretty": "7:51 PM CDT on May 29, 2011",
		"year": "2011",
		"mon": "05",
		"mday": "29",
		"hour": "19",
		"min": "51",
		"tzname": "America/Chicago"
		},
		"utcdate": {
		"pretty": "12:51 AM GMT on May 30, 2011",
		"year": "2011",
		"mon": "05",
		"mday": "30",
		"hour": "00",
		"min": "51",
		"tzname": "UTC"
		},
		"tempm":"21.7", "tempi":"71.1","dewptm":"17.2", "dewpti":"63.0","hum":"75","wspdm":"13.0", "wspdi":"8.1","wgustm":"-9999.0", "wgusti":"-9999.0","wdird":"140","wdire":"SE","vism":"16.1", "visi":"10.0","pressurem":"1011.3", "pressurei":"29.87","windchillm":"-999", "windchilli":"-999","heatindexm":"-9999", "heatindexi":"-9999","precipm":"-9999.00", "precipi":"-9999.00","conds":"Overcast","icon":"cloudy","fog":"0","rain":"0","snow":"0","hail":"0","thunder":"0","tornado":"0","metar":"METAR KMDW 300051Z 14007KT 10SM FEW100 SCT180 OVC300 22/17 A2988 RMK AO2 SLP113 T02170172 $" },
		{
		"date": {
		"pretty": "8:51 PM CDT on May 29, 2011",
		"year": "2011",
		"mon": "05",
		"mday": "29",
		"hour": "20",
		"min": "51",
		"tzname": "America/Chicago"
		},
		"utcdate": {
		"pretty": "1:51 AM GMT on May 30, 2011",
		"year": "2011",
		"mon": "05",
		"mday": "30",
		"hour": "01",
		"min": "51",
		"tzname": "UTC"
		},
		"tempm":"21.7", "tempi":"71.1","dewptm":"17.2", "dewpti":"63.0","hum":"75","wspdm":"13.0", "wspdi":"8.1","wgustm":"-9999.0", "wgusti":"-9999.0","wdird":"130","wdire":"SE","vism":"16.1", "visi":"10.0","pressurem":"1011.4", "pressurei":"29.87","windchillm":"-999", "windchilli":"-999","heatindexm":"-9999", "heatindexi":"-9999","precipm":"-9999.00", "precipi":"-9999.00","conds":"Overcast","icon":"cloudy","fog":"0","rain":"0","snow":"0","hail":"0","thunder":"0","tornado":"0","metar":"METAR KMDW 300151Z 13007KT 10SM FEW110 SCT180 OVC300 22/17 A2988 RMK AO2 SLP114 T02170172 $" },
		{
		"date": {
		"pretty": "9:51 PM CDT on May 29, 2011",
		"year": "2011",
		"mon": "05",
		"mday": "29",
		"hour": "21",
		"min": "51",
		"tzname": "America/Chicago"
		},
		"utcdate": {
		"pretty": "2:51 AM GMT on May 30, 2011",
		"year": "2011",
		"mon": "05",
		"mday": "30",
		"hour": "02",
		"min": "51",
		"tzname": "UTC"
		},
		"tempm":"20.0", "tempi":"68.0","dewptm":"16.7", "dewpti":"62.1","hum":"81","wspdm":"7.4", "wspdi":"4.6","wgustm":"-9999.0", "wgusti":"-9999.0","wdird":"110","wdire":"ESE","vism":"16.1", "visi":"10.0","pressurem":"1012.4", "pressurei":"29.90","windchillm":"-999", "windchilli":"-999","heatindexm":"-9999", "heatindexi":"-9999","precipm":"-9999.00", "precipi":"-9999.00","conds":"Overcast","icon":"cloudy","fog":"0","rain":"0","snow":"0","hail":"0","thunder":"0","tornado":"0","metar":"METAR KMDW 300251Z 11004KT 10SM FEW110 SCT180 OVC300 20/17 A2991 RMK AO2 SLP124 T02000167 53012 $" },
		{
		"date": {
		"pretty": "10:51 PM CDT on May 29, 2011",
		"year": "2011",
		"mon": "05",
		"mday": "29",
		"hour": "22",
		"min": "51",
		"tzname": "America/Chicago"
		},
		"utcdate": {
		"pretty": "3:51 AM GMT on May 30, 2011",
		"year": "2011",
		"mon": "05",
		"mday": "30",
		"hour": "03",
		"min": "51",
		"tzname": "UTC"
		},
		"tempm":"19.4", "tempi":"66.9","dewptm":"16.7", "dewpti":"62.1","hum":"84","wspdm":"11.1", "wspdi":"6.9","wgustm":"-9999.0", "wgusti":"-9999.0","wdird":"130","wdire":"SE","vism":"16.1", "visi":"10.0","pressurem":"1012.9", "pressurei":"29.91","windchillm":"-999", "windchilli":"-999","heatindexm":"-9999", "heatindexi":"-9999","precipm":"-9999.00", "precipi":"-9999.00","conds":"Scattered Clouds","icon":"partlycloudy","fog":"0","rain":"0","snow":"0","hail":"0","thunder":"0","tornado":"0","metar":"METAR KMDW 300351Z 13006KT 10SM FEW180 SCT250 19/17 A2992 RMK AO2 SLP129 T01940167 $" },
		{
		"date": {
		"pretty": "11:51 PM CDT on May 29, 2011",
		"year": "2011",
		"mon": "05",
		"mday": "29",
		"hour": "23",
		"min": "51",
		"tzname": "America/Chicago"
		},
		"utcdate": {
		"pretty": "4:51 AM GMT on May 30, 2011",
		"year": "2011",
		"mon": "05",
		"mday": "30",
		"hour": "04",
		"min": "51",
		"tzname": "UTC"
		},
		"tempm":"20.0", "tempi":"68.0","dewptm":"16.7", "dewpti":"62.1","hum":"81","wspdm":"13.0", "wspdi":"8.1","wgustm":"-9999.0", "wgusti":"-9999.0","wdird":"140","wdire":"SE","vism":"16.1", "visi":"10.0","pressurem":"1012.8", "pressurei":"29.91","windchillm":"-999", "windchilli":"-999","heatindexm":"-9999", "heatindexi":"-9999","precipm":"-9999.00", "precipi":"-9999.00","conds":"Partly Cloudy","icon":"partlycloudy","fog":"0","rain":"0","snow":"0","hail":"0","thunder":"0","tornado":"0","metar":"METAR KMDW 300451Z 14007KT 10SM FEW250 20/17 A2992 RMK AO2 SLP128 T02000167 $" }
		],
		"dailysummary": [
		{ "date": {
		"pretty": "12:00 PM CDT on May 29, 2011",
		"year": "2011",
		"mon": "05",
		"mday": "29",
		"hour": "12",
		"min": "00",
		"tzname": "America/Chicago"
		},
		"fog":"1","rain":"1","snow":"0","snowfallm":"0.00", "snowfalli":"0.00","monthtodatesnowfallm":"", "monthtodatesnowfalli":"","since1julsnowfallm":"", "since1julsnowfalli":"","snowdepthm":"", "snowdepthi":"","hail":"0","thunder":"1","tornado":"0","meantempm":"18", "meantempi":"64","meandewptm":"15", "meandewpti":"59","meanpressurem":"1011", "meanpressurei":"29.87","meanwindspdm":"6", "meanwindspdi":"4","meanwdire":"","meanwdird":"84","meanvism":"6", "meanvisi":"4","humidity":"","maxtempm":"22", "maxtempi":"72","mintempm":"14", "mintempi":"57","maxhumidity":"100","minhumidity":"73","maxdewptm":"17", "maxdewpti":"63","mindewptm":"14", "mindewpti":"57","maxpressurem":"1017", "maxpressurei":"30.05","minpressurem":"1009", "minpressurei":"29.81","maxwspdm":"27", "maxwspdi":"17","minwspdm":"0", "minwspdi":"0","maxvism":"16", "maxvisi":"10","minvism":"0", "minvisi":"0","gdegreedays":"14","heatingdegreedays":"1","coolingdegreedays":"0","precipm":"21.34", "precipi":"0.84","precipsource":"","heatingdegreedaysnormal":"","monthtodateheatingdegreedays":"","monthtodateheatingdegreedaysnormal":"","since1sepheatingdegreedays":"","since1sepheatingdegreedaysnormal":"","since1julheatingdegreedays":"","since1julheatingdegreedaysnormal":"","coolingdegreedaysnormal":"","monthtodatecoolingdegreedays":"","monthtodatecoolingdegreedaysnormal":"","since1sepcoolingdegreedays":"","since1sepcoolingdegreedaysnormal":"","since1jancoolingdegreedays":"","since1jancoolingdegreedaysnormal":"" }
		]
	}
}
