
{
  "response": {
  "version":"0.1",
  "termsofService":"http://www.wunderground.com/weather/api/d/terms.html",
  "features": {
  "history": 1
  }
	}
		,
	"history": {
		"date": {
		"pretty": "June 21, 2014",
		"year": "2014",
		"mon": "06",
		"mday": "21",
		"hour": "12",
		"min": "00",
		"tzname": "America/Chicago"
		},
		"utcdate": {
		"pretty": "June 21, 2014",
		"year": "2014",
		"mon": "06",
		"mday": "21",
		"hour": "17",
		"min": "00",
		"tzname": "UTC"
		},
		"observations": [
		{
		"date": {
		"pretty": "12:53 AM CDT on June 21, 2014",
		"year": "2014",
		"mon": "06",
		"mday": "21",
		"hour": "00",
		"min": "53",
		"tzname": "America/Chicago"
		},
		"utcdate": {
		"pretty": "5:53 AM GMT on June 21, 2014",
		"year": "2014",
		"mon": "06",
		"mday": "21",
		"hour": "05",
		"min": "53",
		"tzname": "UTC"
		},
		"tempm":"22.8", "tempi":"73.0","dewptm":"16.1", "dewpti":"61.0","hum":"66","wspdm":"7.4", "wspdi":"4.6","wgustm":"-9999.0", "wgusti":"-9999.0","wdird":"180","wdire":"South","vism":"16.1", "visi":"10.0","pressurem":"1008.7", "pressurei":"29.79","windchillm":"-999", "windchilli":"-999","heatindexm":"-9999", "heatindexi":"-9999","precipm":"-9999.00", "precipi":"-9999.00","conds":"Clear","icon":"clear","fog":"0","rain":"0","snow":"0","hail":"0","thunder":"0","tornado":"0","metar":"METAR KMIC 210553Z AUTO 18004KT 10SM CLR 23/16 A2980 RMK AO2 SLP087 T02280161 10289 20228 402940200 58005" },
		{
		"date": {
		"pretty": "1:53 AM CDT on June 21, 2014",
		"year": "2014",
		"mon": "06",
		"mday": "21",
		"hour": "01",
		"min": "53",
		"tzname": "America/Chicago"
		},
		"utcdate": {
		"pretty": "6:53 AM GMT on June 21, 2014",
		"year": "2014",
		"mon": "06",
		"mday": "21",
		"hour": "06",
		"min": "53",
		"tzname": "UTC"
		},
		"tempm":"22.2", "tempi":"72.0","dewptm":"17.2", "dewpti":"63.0","hum":"73","wspdm":"5.6", "wspdi":"3.5","wgustm":"-9999.0", "wgusti":"-9999.0","wdird":"230","wdire":"SW","vism":"16.1", "visi":"10.0","pressurem":"1009.3", "pressurei":"29.81","windchillm":"-999", "windchilli":"-999","heatindexm":"-9999", "heatindexi":"-9999","precipm":"-9999.00", "precipi":"-9999.00","conds":"Clear","icon":"clear","fog":"0","rain":"0","snow":"0","hail":"0","thunder":"0","tornado":"0","metar":"METAR KMIC 210653Z AUTO 23003KT 10SM CLR 22/17 A2982 RMK AO2 SLP093 T02220172" },
		{
		"date": {
		"pretty": "2:53 AM CDT on June 21, 2014",
		"year": "2014",
		"mon": "06",
		"mday": "21",
		"hour": "02",
		"min": "53",
		"tzname": "America/Chicago"
		},
		"utcdate": {
		"pretty": "7:53 AM GMT on June 21, 2014",
		"year": "2014",
		"mon": "06",
		"mday": "21",
		"hour": "07",
		"min": "53",
		"tzname": "UTC"
		},
		"tempm":"22.2", "tempi":"72.0","dewptm":"17.2", "dewpti":"63.0","hum":"73","wspdm":"11.1", "wspdi":"6.9","wgustm":"-9999.0", "wgusti":"-9999.0","wdird":"300","wdire":"WNW","vism":"16.1", "visi":"10.0","pressurem":"1009.9", "pressurei":"29.83","windchillm":"-999", "windchilli":"-999","heatindexm":"-9999", "heatindexi":"-9999","precipm":"-9999.00", "precipi":"-9999.00","conds":"Clear","icon":"clear","fog":"0","rain":"0","snow":"0","hail":"0","thunder":"0","tornado":"0","metar":"METAR KMIC 210753Z AUTO 30006KT 10SM CLR 22/17 A2984 RMK AO2 SLP099 T02220172" },
		{
		"date": {
		"pretty": "3:53 AM CDT on June 21, 2014",
		"year": "2014",
		"mon": "06",
		"mday": "21",
		"hour": "03",
		"min": "53",
		"tzname": "America/Chicago"
		},
		"utcdate": {
		"pretty": "8:53 AM GMT on June 21, 2014",
		"year": "2014",
		"mon": "06",
		"mday": "21",
		"hour": "08",
		"min": "53",
		"tzname": "UTC"
		},
		"tempm":"21.1", "tempi":"70.0","dewptm":"16.7", "dewpti":"62.1","hum":"76","wspdm":"7.4", "wspdi":"4.6","wgustm":"-9999.0", "wgusti":"-9999.0","wdird":"320","wdire":"NW","vism":"16.1", "visi":"10.0","pressurem":"1009.7", "pressurei":"29.82","windchillm":"-999", "windchilli":"-999","heatindexm":"-9999", "heatindexi":"-9999","precipm":"-9999.00", "precipi":"-9999.00","conds":"Clear","icon":"clear","fog":"0","rain":"0","snow":"0","hail":"0","thunder":"0","tornado":"0","metar":"METAR KMIC 210853Z AUTO 32004KT 10SM CLR 21/17 A2984 RMK AO2 SLP097 T02110167 50010" },
		{
		"date": {
		"pretty": "4:53 AM CDT on June 21, 2014",
		"year": "2014",
		"mon": "06",
		"mday": "21",
		"hour": "04",
		"min": "53",
		"tzname": "America/Chicago"
		},
		"utcdate": {
		"pretty": "9:53 AM GMT on June 21, 2014",
		"year": "2014",
		"mon": "06",
		"mday": "21",
		"hour": "09",
		"min": "53",
		"tzname": "UTC"
		},
		"tempm":"18.9", "tempi":"66.0","dewptm":"16.1", "dewpti":"61.0","hum":"84","wspdm":"9.3", "wspdi":"5.8","wgustm":"-9999.0", "wgusti":"-9999.0","wdird":"350","wdire":"North","vism":"16.1", "visi":"10.0","pressurem":"1010.2", "pressurei":"29.83","windchillm":"-999", "windchilli":"-999","heatindexm":"-9999", "heatindexi":"-9999","precipm":"-9999.00", "precipi":"-9999.00","conds":"Clear","icon":"clear","fog":"0","rain":"0","snow":"0","hail":"0","thunder":"0","tornado":"0","metar":"METAR KMIC 210953Z AUTO 35005KT 10SM CLR 19/16 A2985 RMK AO2 SLP102 T01890161" },
		{
		"date": {
		"pretty": "5:53 AM CDT on June 21, 2014",
		"year": "2014",
		"mon": "06",
		"mday": "21",
		"hour": "05",
		"min": "53",
		"tzname": "America/Chicago"
		},
		"utcdate": {
		"pretty": "10:53 AM GMT on June 21, 2014",
		"year": "2014",
		"mon": "06",
		"mday": "21",
		"hour": "10",
		"min": "53",
		"tzname": "UTC"
		},
		"tempm":"17.8", "tempi":"64.0","dewptm":"15.0", "dewpti":"59.0","hum":"84","wspdm":"5.6", "wspdi":"3.5","wgustm":"-9999.0", "wgusti":"-9999.0","wdird":"10","wdire":"North","vism":"14.5", "visi":"9.0","pressurem":"1011.5", "pressurei":"29.87","windchillm":"-999", "windchilli":"-999","heatindexm":"-9999", "heatindexi":"-9999","precipm":"-9999.00", "precipi":"-9999.00","conds":"Clear","icon":"clear","fog":"0","rain":"0","snow":"0","hail":"0","thunder":"0","tornado":"0","metar":"METAR KMIC 211053Z AUTO 01003KT 9SM CLR 18/15 A2989 RMK AO2 SLP115 T01780150" },
		{
		"date": {
		"pretty": "6:53 AM CDT on June 21, 2014",
		"year": "2014",
		"mon": "06",
		"mday": "21",
		"hour": "06",
		"min": "53",
		"tzname": "America/Chicago"
		},
		"utcdate": {
		"pretty": "11:53 AM GMT on June 21, 2014",
		"year": "2014",
		"mon": "06",
		"mday": "21",
		"hour": "11",
		"min": "53",
		"tzname": "UTC"
		},
		"tempm":"17.8", "tempi":"64.0","dewptm":"15.0", "dewpti":"59.0","hum":"84","wspdm":"9.3", "wspdi":"5.8","wgustm":"-9999.0", "wgusti":"-9999.0","wdird":"340","wdire":"NNW","vism":"16.1", "visi":"10.0","pressurem":"1012.1", "pressurei":"29.89","windchillm":"-999", "windchilli":"-999","heatindexm":"-9999", "heatindexi":"-9999","precipm":"-9999.00", "precipi":"-9999.00","conds":"Clear","icon":"clear","fog":"0","rain":"0","snow":"0","hail":"0","thunder":"0","tornado":"0","metar":"METAR KMIC 211153Z 34005KT 10SM CLR 18/15 A2990 RMK AO2 SLP121 T01780150 10228 20178 53021" },
		{
		"date": {
		"pretty": "7:53 AM CDT on June 21, 2014",
		"year": "2014",
		"mon": "06",
		"mday": "21",
		"hour": "07",
		"min": "53",
		"tzname": "America/Chicago"
		},
		"utcdate": {
		"pretty": "12:53 PM GMT on June 21, 2014",
		"year": "2014",
		"mon": "06",
		"mday": "21",
		"hour": "12",
		"min": "53",
		"tzname": "UTC"
		},
		"tempm":"19.4", "tempi":"66.9","dewptm":"15.6", "dewpti":"60.1","hum":"79","wspdm":"7.4", "wspdi":"4.6","wgustm":"-9999.0", "wgusti":"-9999.0","wdird":"20","wdire":"NNE","vism":"16.1", "visi":"10.0","pressurem":"1012.4", "pressurei":"29.90","windchillm":"-999", "windchilli":"-999","heatindexm":"-9999", "heatindexi":"-9999","precipm":"-9999.00", "precipi":"-9999.00","conds":"Clear","icon":"clear","fog":"0","rain":"0","snow":"0","hail":"0","thunder":"0","tornado":"0","metar":"METAR KMIC 211253Z 02004KT 10SM CLR 19/16 A2991 RMK AO2 SLP124 T01940156" },
		{
		"date": {
		"pretty": "8:53 AM CDT on June 21, 2014",
		"year": "2014",
		"mon": "06",
		"mday": "21",
		"hour": "08",
		"min": "53",
		"tzname": "America/Chicago"
		},
		"utcdate": {
		"pretty": "1:53 PM GMT on June 21, 2014",
		"year": "2014",
		"mon": "06",
		"mday": "21",
		"hour": "13",
		"min": "53",
		"tzname": "UTC"
		},
		"tempm":"20.6", "tempi":"69.1","dewptm":"15.6", "dewpti":"60.1","hum":"73","wspdm":"7.4", "wspdi":"4.6","wgustm":"-9999.0", "wgusti":"-9999.0","wdird":"30","wdire":"NNE","vism":"16.1", "visi":"10.0","pressurem":"1012.4", "pressurei":"29.90","windchillm":"-999", "windchilli":"-999","heatindexm":"-9999", "heatindexi":"-9999","precipm":"-9999.00", "precipi":"-9999.00","conds":"Clear","icon":"clear","fog":"0","rain":"0","snow":"0","hail":"0","thunder":"0","tornado":"0","metar":"METAR KMIC 211353Z 03004KT 10SM CLR 21/16 A2991 RMK AO2 SLP124 T02060156" },
		{
		"date": {
		"pretty": "9:53 AM CDT on June 21, 2014",
		"year": "2014",
		"mon": "06",
		"mday": "21",
		"hour": "09",
		"min": "53",
		"tzname": "America/Chicago"
		},
		"utcdate": {
		"pretty": "2:53 PM GMT on June 21, 2014",
		"year": "2014",
		"mon": "06",
		"mday": "21",
		"hour": "14",
		"min": "53",
		"tzname": "UTC"
		},
		"tempm":"22.8", "tempi":"73.0","dewptm":"15.0", "dewpti":"59.0","hum":"61","wspdm":"7.4", "wspdi":"4.6","wgustm":"-9999.0", "wgusti":"-9999.0","wdird":"0","wdire":"Variable","vism":"16.1", "visi":"10.0","pressurem":"1012.4", "pressurei":"29.90","windchillm":"-999", "windchilli":"-999","heatindexm":"-9999", "heatindexi":"-9999","precipm":"-9999.00", "precipi":"-9999.00","conds":"Clear","icon":"clear","fog":"0","rain":"0","snow":"0","hail":"0","thunder":"0","tornado":"0","metar":"METAR KMIC 211453Z VRB04KT 10SM CLR 23/15 A2991 RMK AO2 SLP124 T02280150 51004" },
		{
		"date": {
		"pretty": "10:53 AM CDT on June 21, 2014",
		"year": "2014",
		"mon": "06",
		"mday": "21",
		"hour": "10",
		"min": "53",
		"tzname": "America/Chicago"
		},
		"utcdate": {
		"pretty": "3:53 PM GMT on June 21, 2014",
		"year": "2014",
		"mon": "06",
		"mday": "21",
		"hour": "15",
		"min": "53",
		"tzname": "UTC"
		},
		"tempm":"25.0", "tempi":"77.0","dewptm":"13.9", "dewpti":"57.0","hum":"50","wspdm":"9.3", "wspdi":"5.8","wgustm":"-9999.0", "wgusti":"-9999.0","wdird":"30","wdire":"NNE","vism":"16.1", "visi":"10.0","pressurem":"1012.1", "pressurei":"29.89","windchillm":"-999", "windchilli":"-999","heatindexm":"-9999", "heatindexi":"-9999","precipm":"-9999.00", "precipi":"-9999.00","conds":"Clear","icon":"clear","fog":"0","rain":"0","snow":"0","hail":"0","thunder":"0","tornado":"0","metar":"METAR KMIC 211553Z 03005KT 10SM CLR 25/14 A2991 RMK AO2 SLP121 T02500139" },
		{
		"date": {
		"pretty": "11:53 AM CDT on June 21, 2014",
		"year": "2014",
		"mon": "06",
		"mday": "21",
		"hour": "11",
		"min": "53",
		"tzname": "America/Chicago"
		},
		"utcdate": {
		"pretty": "4:53 PM GMT on June 21, 2014",
		"year": "2014",
		"mon": "06",
		"mday": "21",
		"hour": "16",
		"min": "53",
		"tzname": "UTC"
		},
		"tempm":"25.6", "tempi":"78.1","dewptm":"15.0", "dewpti":"59.0","hum":"52","wspdm":"9.3", "wspdi":"5.8","wgustm":"-9999.0", "wgusti":"-9999.0","wdird":"40","wdire":"NE","vism":"16.1", "visi":"10.0","pressurem":"1012.1", "pressurei":"29.89","windchillm":"-999", "windchilli":"-999","heatindexm":"-9999", "heatindexi":"-9999","precipm":"-9999.00", "precipi":"-9999.00","conds":"Clear","icon":"clear","fog":"0","rain":"0","snow":"0","hail":"0","thunder":"0","tornado":"0","metar":"METAR KMIC 211653Z 04005KT 10SM CLR 26/15 A2991 RMK AO2 SLP121 T02560150" },
		{
		"date": {
		"pretty": "12:53 PM CDT on June 21, 2014",
		"year": "2014",
		"mon": "06",
		"mday": "21",
		"hour": "12",
		"min": "53",
		"tzname": "America/Chicago"
		},
		"utcdate": {
		"pretty": "5:53 PM GMT on June 21, 2014",
		"year": "2014",
		"mon": "06",
		"mday": "21",
		"hour": "17",
		"min": "53",
		"tzname": "UTC"
		},
		"tempm":"26.7", "tempi":"80.1","dewptm":"13.3", "dewpti":"55.9","hum":"43","wspdm":"7.4", "wspdi":"4.6","wgustm":"-9999.0", "wgusti":"-9999.0","wdird":"60","wdire":"ENE","vism":"16.1", "visi":"10.0","pressurem":"1012.4", "pressurei":"29.90","windchillm":"-999", "windchilli":"-999","heatindexm":"26.8", "heatindexi":"80.2","precipm":"-9999.00", "precipi":"-9999.00","conds":"Clear","icon":"clear","fog":"0","rain":"0","snow":"0","hail":"0","thunder":"0","tornado":"0","metar":"METAR KMIC 211753Z 06004KT 10SM CLR 27/13 A2991 RMK AO2 SLP124 T02670133 10267 20178 55000" },
		{
		"date": {
		"pretty": "1:53 PM CDT on June 21, 2014",
		"year": "2014",
		"mon": "06",
		"mday": "21",
		"hour": "13",
		"min": "53",
		"tzname": "America/Chicago"
		},
		"utcdate": {
		"pretty": "6:53 PM GMT on June 21, 2014",
		"year": "2014",
		"mon": "06",
		"mday": "21",
		"hour": "18",
		"min": "53",
		"tzname": "UTC"
		},
		"tempm":"27.8", "tempi":"82.0","dewptm":"13.3", "dewpti":"55.9","hum":"41","wspdm":"9.3", "wspdi":"5.8","wgustm":"-9999.0", "wgusti":"-9999.0","wdird":"40","wdire":"NE","vism":"16.1", "visi":"10.0","pressurem":"1012.2", "pressurei":"29.89","windchillm":"-999", "windchilli":"-999","heatindexm":"27.6", "heatindexi":"81.6","precipm":"-9999.00", "precipi":"-9999.00","conds":"Clear","icon":"clear","fog":"0","rain":"0","snow":"0","hail":"0","thunder":"0","tornado":"0","metar":"METAR KMIC 211853Z 04005KT 10SM CLR 28/13 A2991 RMK AO2 SLP122 T02780133" },
		{
		"date": {
		"pretty": "2:53 PM CDT on June 21, 2014",
		"year": "2014",
		"mon": "06",
		"mday": "21",
		"hour": "14",
		"min": "53",
		"tzname": "America/Chicago"
		},
		"utcdate": {
		"pretty": "7:53 PM GMT on June 21, 2014",
		"year": "2014",
		"mon": "06",
		"mday": "21",
		"hour": "19",
		"min": "53",
		"tzname": "UTC"
		},
		"tempm":"28.9", "tempi":"84.0","dewptm":"13.3", "dewpti":"55.9","hum":"38","wspdm":"9.3", "wspdi":"5.8","wgustm":"-9999.0", "wgusti":"-9999.0","wdird":"30","wdire":"NNE","vism":"16.1", "visi":"10.0","pressurem":"1011.8", "pressurei":"29.88","windchillm":"-999", "windchilli":"-999","heatindexm":"28.3", "heatindexi":"83.0","precipm":"-9999.00", "precipi":"-9999.00","conds":"Clear","icon":"clear","fog":"0","rain":"0","snow":"0","hail":"0","thunder":"0","tornado":"0","metar":"METAR KMIC 211953Z 03005KT 10SM CLR 29/13 A2990 RMK AO2 SLP118 T02890133" },
		{
		"date": {
		"pretty": "3:53 PM CDT on June 21, 2014",
		"year": "2014",
		"mon": "06",
		"mday": "21",
		"hour": "15",
		"min": "53",
		"tzname": "America/Chicago"
		},
		"utcdate": {
		"pretty": "8:53 PM GMT on June 21, 2014",
		"year": "2014",
		"mon": "06",
		"mday": "21",
		"hour": "20",
		"min": "53",
		"tzname": "UTC"
		},
		"tempm":"28.3", "tempi":"82.9","dewptm":"12.8", "dewpti":"55.0","hum":"38","wspdm":"7.4", "wspdi":"4.6","wgustm":"-9999.0", "wgusti":"-9999.0","wdird":"90","wdire":"East","vism":"16.1", "visi":"10.0","pressurem":"1012.0", "pressurei":"29.89","windchillm":"-999", "windchilli":"-999","heatindexm":"27.8", "heatindexi":"82.0","precipm":"-9999.00", "precipi":"-9999.00","conds":"Clear","icon":"clear","fog":"0","rain":"0","snow":"0","hail":"0","thunder":"0","tornado":"0","metar":"METAR KMIC 212053Z AUTO 09004KT 10SM CLR 28/13 A2990 RMK AO2 SLP120 T02830128 55004" },
		{
		"date": {
		"pretty": "4:53 PM CDT on June 21, 2014",
		"year": "2014",
		"mon": "06",
		"mday": "21",
		"hour": "16",
		"min": "53",
		"tzname": "America/Chicago"
		},
		"utcdate": {
		"pretty": "9:53 PM GMT on June 21, 2014",
		"year": "2014",
		"mon": "06",
		"mday": "21",
		"hour": "21",
		"min": "53",
		"tzname": "UTC"
		},
		"tempm":"28.9", "tempi":"84.0","dewptm":"13.3", "dewpti":"55.9","hum":"38","wspdm":"9.3", "wspdi":"5.8","wgustm":"-9999.0", "wgusti":"-9999.0","wdird":"0","wdire":"Variable","vism":"16.1", "visi":"10.0","pressurem":"1011.6", "pressurei":"29.88","windchillm":"-999", "windchilli":"-999","heatindexm":"28.3", "heatindexi":"83.0","precipm":"-9999.00", "precipi":"-9999.00","conds":"Clear","icon":"clear","fog":"0","rain":"0","snow":"0","hail":"0","thunder":"0","tornado":"0","metar":"METAR KMIC 212153Z AUTO VRB05KT 10SM CLR 29/13 A2989 RMK AO2 SLP116 T02890133" },
		{
		"date": {
		"pretty": "5:53 PM CDT on June 21, 2014",
		"year": "2014",
		"mon": "06",
		"mday": "21",
		"hour": "17",
		"min": "53",
		"tzname": "America/Chicago"
		},
		"utcdate": {
		"pretty": "10:53 PM GMT on June 21, 2014",
		"year": "2014",
		"mon": "06",
		"mday": "21",
		"hour": "22",
		"min": "53",
		"tzname": "UTC"
		},
		"tempm":"28.3", "tempi":"82.9","dewptm":"12.8", "dewpti":"55.0","hum":"38","wspdm":"0.0", "wspdi":"0.0","wgustm":"-9999.0", "wgusti":"-9999.0","wdird":"0","wdire":"North","vism":"16.1", "visi":"10.0","pressurem":"1011.2", "pressurei":"29.86","windchillm":"-999", "windchilli":"-999","heatindexm":"27.8", "heatindexi":"82.0","precipm":"-9999.00", "precipi":"-9999.00","conds":"Clear","icon":"clear","fog":"0","rain":"0","snow":"0","hail":"0","thunder":"0","tornado":"0","metar":"METAR KMIC 212253Z AUTO 00000KT 10SM CLR 28/13 A2988 RMK AO2 SLP112 T02830128" },
		{
		"date": {
		"pretty": "6:53 PM CDT on June 21, 2014",
		"year": "2014",
		"mon": "06",
		"mday": "21",
		"hour": "18",
		"min": "53",
		"tzname": "America/Chicago"
		},
		"utcdate": {
		"pretty": "11:53 PM GMT on June 21, 2014",
		"year": "2014",
		"mon": "06",
		"mday": "21",
		"hour": "23",
		"min": "53",
		"tzname": "UTC"
		},
		"tempm":"28.3", "tempi":"82.9","dewptm":"13.3", "dewpti":"55.9","hum":"39","wspdm":"11.1", "wspdi":"6.9","wgustm":"-9999.0", "wgusti":"-9999.0","wdird":"110","wdire":"ESE","vism":"16.1", "visi":"10.0","pressurem":"1010.6", "pressurei":"29.85","windchillm":"-999", "windchilli":"-999","heatindexm":"27.9", "heatindexi":"82.1","precipm":"-9999.00", "precipi":"-9999.00","conds":"Clear","icon":"clear","fog":"0","rain":"0","snow":"0","hail":"0","thunder":"0","tornado":"0","metar":"METAR KMIC 212353Z 11006KT 10SM CLR 28/13 A2986 RMK AO2 SLP106 T02830133 10300 20267 58014" },
		{
		"date": {
		"pretty": "7:53 PM CDT on June 21, 2014",
		"year": "2014",
		"mon": "06",
		"mday": "21",
		"hour": "19",
		"min": "53",
		"tzname": "America/Chicago"
		},
		"utcdate": {
		"pretty": "12:53 AM GMT on June 22, 2014",
		"year": "2014",
		"mon": "06",
		"mday": "22",
		"hour": "00",
		"min": "53",
		"tzname": "UTC"
		},
		"tempm":"27.2", "tempi":"81.0","dewptm":"12.8", "dewpti":"55.0","hum":"41","wspdm":"7.4", "wspdi":"4.6","wgustm":"-9999.0", "wgusti":"-9999.0","wdird":"110","wdire":"ESE","vism":"16.1", "visi":"10.0","pressurem":"1010.1", "pressurei":"29.83","windchillm":"-999", "windchilli":"-999","heatindexm":"27.1", "heatindexi":"80.7","precipm":"-9999.00", "precipi":"-9999.00","conds":"Clear","icon":"clear","fog":"0","rain":"0","snow":"0","hail":"0","thunder":"0","tornado":"0","metar":"METAR KMIC 220053Z 11004KT 10SM CLR 27/13 A2984 RMK AO2 SLP101 T02720128" },
		{
		"date": {
		"pretty": "8:53 PM CDT on June 21, 2014",
		"year": "2014",
		"mon": "06",
		"mday": "21",
		"hour": "20",
		"min": "53",
		"tzname": "America/Chicago"
		},
		"utcdate": {
		"pretty": "1:53 AM GMT on June 22, 2014",
		"year": "2014",
		"mon": "06",
		"mday": "22",
		"hour": "01",
		"min": "53",
		"tzname": "UTC"
		},
		"tempm":"25.6", "tempi":"78.1","dewptm":"12.8", "dewpti":"55.0","hum":"45","wspdm":"7.4", "wspdi":"4.6","wgustm":"-9999.0", "wgusti":"-9999.0","wdird":"110","wdire":"ESE","vism":"16.1", "visi":"10.0","pressurem":"1010.1", "pressurei":"29.83","windchillm":"-999", "windchilli":"-999","heatindexm":"-9999", "heatindexi":"-9999","precipm":"-9999.00", "precipi":"-9999.00","conds":"Clear","icon":"clear","fog":"0","rain":"0","snow":"0","hail":"0","thunder":"0","tornado":"0","metar":"METAR KMIC 220153Z 11004KT 10SM CLR 26/13 A2984 RMK AO2 SLP101 T02560128" },
		{
		"date": {
		"pretty": "9:53 PM CDT on June 21, 2014",
		"year": "2014",
		"mon": "06",
		"mday": "21",
		"hour": "21",
		"min": "53",
		"tzname": "America/Chicago"
		},
		"utcdate": {
		"pretty": "2:53 AM GMT on June 22, 2014",
		"year": "2014",
		"mon": "06",
		"mday": "22",
		"hour": "02",
		"min": "53",
		"tzname": "UTC"
		},
		"tempm":"23.3", "tempi":"73.9","dewptm":"13.9", "dewpti":"57.0","hum":"55","wspdm":"5.6", "wspdi":"3.5","wgustm":"-9999.0", "wgusti":"-9999.0","wdird":"100","wdire":"East","vism":"16.1", "visi":"10.0","pressurem":"1010.6", "pressurei":"29.85","windchillm":"-999", "windchilli":"-999","heatindexm":"-9999", "heatindexi":"-9999","precipm":"-9999.00", "precipi":"-9999.00","conds":"Clear","icon":"clear","fog":"0","rain":"0","snow":"0","hail":"0","thunder":"0","tornado":"0","metar":"METAR KMIC 220253Z AUTO 10003KT 10SM CLR 23/14 A2986 RMK AO2 SLP106 T02330139 55000" },
		{
		"date": {
		"pretty": "10:53 PM CDT on June 21, 2014",
		"year": "2014",
		"mon": "06",
		"mday": "21",
		"hour": "22",
		"min": "53",
		"tzname": "America/Chicago"
		},
		"utcdate": {
		"pretty": "3:53 AM GMT on June 22, 2014",
		"year": "2014",
		"mon": "06",
		"mday": "22",
		"hour": "03",
		"min": "53",
		"tzname": "UTC"
		},
		"tempm":"22.2", "tempi":"72.0","dewptm":"15.0", "dewpti":"59.0","hum":"64","wspdm":"5.6", "wspdi":"3.5","wgustm":"-9999.0", "wgusti":"-9999.0","wdird":"140","wdire":"SE","vism":"14.5", "visi":"9.0","pressurem":"1010.7", "pressurei":"29.85","windchillm":"-999", "windchilli":"-999","heatindexm":"-9999", "heatindexi":"-9999","precipm":"-9999.00", "precipi":"-9999.00","conds":"Clear","icon":"clear","fog":"0","rain":"0","snow":"0","hail":"0","thunder":"0","tornado":"0","metar":"METAR KMIC 220353Z AUTO 14003KT 9SM CLR 22/15 A2986 RMK AO2 SLP107 T02220150" },
		{
		"date": {
		"pretty": "11:53 PM CDT on June 21, 2014",
		"year": "2014",
		"mon": "06",
		"mday": "21",
		"hour": "23",
		"min": "53",
		"tzname": "America/Chicago"
		},
		"utcdate": {
		"pretty": "4:53 AM GMT on June 22, 2014",
		"year": "2014",
		"mon": "06",
		"mday": "22",
		"hour": "04",
		"min": "53",
		"tzname": "UTC"
		},
		"tempm":"21.7", "tempi":"71.1","dewptm":"13.9", "dewpti":"57.0","hum":"61","wspdm":"9.3", "wspdi":"5.8","wgustm":"-9999.0", "wgusti":"-9999.0","wdird":"180","wdire":"South","vism":"16.1", "visi":"10.0","pressurem":"1011.5", "pressurei":"29.87","windchillm":"-999", "windchilli":"-999","heatindexm":"-9999", "heatindexi":"-9999","precipm":"-9999.00", "precipi":"-9999.00","conds":"Clear","icon":"clear","fog":"0","rain":"0","snow":"0","hail":"0","thunder":"0","tornado":"0","metar":"METAR KMIC 220453Z AUTO 18005KT 10SM CLR 22/14 A2989 RMK AO2 SLP115 T02170139" }
		],
		"dailysummary": [
		{ "date": {
		"pretty": "12:00 PM CDT on June 21, 2014",
		"year": "2014",
		"mon": "06",
		"mday": "21",
		"hour": "12",
		"min": "00",
		"tzname": "America/Chicago"
		},
		"fog":"0","rain":"0","snow":"0","snowfallm":"0.00", "snowfalli":"0.00","monthtodatesnowfallm":"", "monthtodatesnowfalli":"","since1julsnowfallm":"", "since1julsnowfalli":"","snowdepthm":"", "snowdepthi":"","hail":"0","thunder":"0","tornado":"0","meantempm":"23", "meantempi":"74","meandewptm":"14", "meandewpti":"58","meanpressurem":"1011", "meanpressurei":"29.86","meanwindspdm":"8", "meanwindspdi":"5","meanwdire":"","meanwdird":"53","meanvism":"16", "meanvisi":"10","humidity":"","maxtempm":"30", "maxtempi":"86","mintempm":"18", "mintempi":"64","maxhumidity":"84","minhumidity":"38","maxdewptm":"17", "maxdewpti":"63","mindewptm":"13", "mindewpti":"55","maxpressurem":"1012", "maxpressurei":"29.90","minpressurem":"1009", "minpressurei":"29.79","maxwspdm":"11", "maxwspdi":"7","minwspdm":"0", "minwspdi":"0","maxvism":"16", "maxvisi":"10","minvism":"14", "minvisi":"9","gdegreedays":"24","heatingdegreedays":"0","coolingdegreedays":"9","precipm":"0.00", "precipi":"0.00","precipsource":"","heatingdegreedaysnormal":"","monthtodateheatingdegreedays":"","monthtodateheatingdegreedaysnormal":"","since1sepheatingdegreedays":"","since1sepheatingdegreedaysnormal":"","since1julheatingdegreedays":"","since1julheatingdegreedaysnormal":"","coolingdegreedaysnormal":"","monthtodatecoolingdegreedays":"","monthtodatecoolingdegreedaysnormal":"","since1sepcoolingdegreedays":"","since1sepcoolingdegreedaysnormal":"","since1jancoolingdegreedays":"","since1jancoolingdegreedaysnormal":"" }
		]
	}
}
